{
  "获取时间": "2026-03-20 18:36:04",
  "数据日期": "2026-03-17",
  "数据条数": 20,
  "研报数据": [
    {
      "序号": 1,
      "报告日期": "2026-03-17",
      "证券代码": "001979",
      "证券简称": "招商蛇口",
      "评级": "买入",
      "评级变化": "维持",
      "目标价": "--",
      "EPS实际值(元)": "0.08(2025)",
      "T年度": "2026",
      "EPS预测": {
        "T年": "0.14",
        "T+1年": "0.19",
        "T+2年": "0.24"
      },
      "标题": "招商蛇口(001979)2025年报点评：收入利润下滑，投资聚焦核心",
      "研究机构": "银河证券"
    },
    {
      "序号": 2,
      "报告日期": "2026-03-17",
      "证券代码": "301536",
      "证券简称": "星宸科技",
      "评级": "买入",
      "评级变化": "首次",
      "目标价": "--",
      "EPS实际值(元)": "0.73(2025)",
      "T年度": "2026",
      "EPS预测": {
        "T年": "1.46",
        "T+1年": "1.88",
        "T+2年": "2.18"
      },
      "标题": "星宸科技(301536)2025年报点评：内生外延共驱业绩成长",
      "研究机构": "财信证券"
    },
    {
      "序号": 3,
      "报告日期": "2026-03-17",
      "证券代码": "688615",
      "证券简称": "合合信息",
      "评级": "买入",
      "评级变化": "维持",
      "目标价": "--",
      "EPS实际值(元)": "3.24(2025)",
      "T年度": "2026",
      "EPS预测": {
        "T年": "3.94",
        "T+1年": "4.92",
        "T+2年": "6.35"
      },
      "标题": "合合信息(688615)AI赋能产品矩阵，海外业务表现亮眼",
      "研究机构": "银河证券"
    },
    {
      "序号": 4,
      "报告日期": "2026-03-17",
      "证券代码": "000415",
      "证券简称": "渤海租赁",
      "评级": "买入",
      "评级变化": "首次",
      "目标价": "5.75",
      "EPS实际值(元)": "0.1462(2024)",
      "T年度": "2025",
      "EPS预测": {
        "T年": "-0.05",
        "T+1年": "0.35",
        "T+2年": "0.47"
      },
      "标题": "渤海租赁(000415)全球飞机租赁龙头再起航",
      "研究机构": "国金证券"
    },
    {
      "序号": 5,
      "报告日期": "2026-03-17",
      "证券代码": "001979",
      "证券简称": "招商蛇口",
      "评级": "买入",
      "评级变化": "维持",
      "目标价": "12.08",
      "EPS实际值(元)": "0.08(2025)",
      "T年度": "2026",
      "EPS预测": {
        "T年": "0.15",
        "T+1年": "0.19",
        "T+2年": "0.25"
      },
      "标题": "招商蛇口(001979)盈利筑底，核心城市扩张提速",
      "研究机构": "华泰证券"
    },
    {
      "序号": 6,
      "报告日期": "2026-03-17",
      "证券代码": "002709",
      "证券简称": "天赐材料",
      "评级": "买入",
      "评级变化": "维持",
      "目标价": "--",
      "EPS实际值(元)": "0.71(2025)",
      "T年度": "2026",
      "EPS预测": {
        "T年": "3.61",
        "T+1年": "4.36",
        "T+2年": "5.31"
      },
      "标题": "天赐材料(002709)2025年年报点评：6F涨价兑现业绩，期待新业务拓张和出海布局",
      "研究机构": "长江证券"
    },
    {
      "序号": 7,
      "报告日期": "2026-03-17",
      "证券代码": "002859",
      "证券简称": "洁美科技",
      "评级": "买入",
      "评级变化": "维持",
      "目标价": "--",
      "EPS实际值(元)": "0.47(2024)",
      "T年度": "2025",
      "EPS预测": {
        "T年": "0.61",
        "T+1年": "1.01",
        "T+2年": "1.52"
      },
      "标题": "洁美科技(002859)拟收购埃福思进军超精密加工设备领域，主业下游景气度上行",
      "研究机构": "华西证券"
    },
    {
      "序号": 8,
      "报告日期": "2026-03-17",
      "证券代码": "300476",
      "证券简称": "胜宏科技",
      "评级": "增持",
      "评级变化": "维持",
      "目标价": "--",
      "EPS实际值(元)": "5.01(2025)",
      "T年度": "2026",
      "EPS预测": {
        "T年": "11.05",
        "T+1年": "17.38",
        "T+2年": "23.52"
      },
      "标题": "胜宏科技(300476)AI助力PCB行业升格，新扩产能打开增长空间",
      "研究机构": "平安证券"
    },
    {
      "序号": 9,
      "报告日期": "2026-03-17",
      "证券代码": "600054",
      "证券简称": "黄山旅游",
      "评级": "买入",
      "评级变化": "维持",
      "目标价": "16.88",
      "EPS实际值(元)": "0.43(2024)",
      "T年度": "2025",
      "EPS预测": {
        "T年": "0.40",
        "T+1年": "0.48",
        "T+2年": "0.55"
      },
      "标题": "黄山旅游(600054)东海索道+黄山温泉，关注增量项目成长性",
      "研究机构": "广发证券"
    },
    {
      "序号": 10,
      "报告日期": "2026-03-17",
      "证券代码": "600282",
      "证券简称": "南钢股份",
      "评级": "买入",
      "评级变化": "维持",
      "目标价": "--",
      "EPS实际值(元)": "0.4651(2025)",
      "T年度": "2026",
      "EPS预测": {
        "T年": "0.53",
        "T+1年": "0.59",
        "T+2年": "0.67"
      },
      "标题": "南钢股份(600282)2025年报点评：产品结构调整优化+盈利能力提升，年报业绩超预期",
      "研究机构": "西部证券"
    },
    {
      "序号": 11,
      "报告日期": "2026-03-17",
      "证券代码": "603317",
      "证券简称": "天味食品",
      "评级": "增持",
      "评级变化": "维持",
      "目标价": "--",
      "EPS实际值(元)": "0.5386(2025)",
      "T年度": "2026",
      "EPS预测": {
        "T年": "0.64",
        "T+1年": "0.72",
        "T+2年": "0.77"
      },
      "标题": "天味食品(603317)重建经营底盘，积极分红回馈股东",
      "研究机构": "国信证券"
    },
    {
      "序号": 12,
      "报告日期": "2026-03-17",
      "证券代码": "603558",
      "证券简称": "健盛集团",
      "评级": "未知",
      "评级变化": "未知",
      "目标价": "15.79",
      "EPS实际值(元)": "1.12(2025)",
      "T年度": "2026",
      "EPS预测": {
        "T年": "--",
        "T+1年": "--",
        "T+2年": "--"
      },
      "标题": "健盛集团(603558)波动环境下棉袜稳健，无缝服饰盈利改善",
      "研究机构": "中金公司"
    },
    {
      "序号": 13,
      "报告日期": "2026-03-17",
      "证券代码": "688123",
      "证券简称": "聚辰股份",
      "评级": "买入",
      "评级变化": "维持",
      "目标价": "--",
      "EPS实际值(元)": "1.84(2024)",
      "T年度": "2025",
      "EPS预测": {
        "T年": "2.29",
        "T+1年": "3.24",
        "T+2年": "3.94"
      },
      "标题": "聚辰股份(688123)跟踪报告之十：业绩快速增长，存储类芯片市场空间广阔",
      "研究机构": "光大证券"
    },
    {
      "序号": 14,
      "报告日期": "2026-03-17",
      "证券代码": "688630",
      "证券简称": "芯碁微装",
      "评级": "买入",
      "评级变化": "首次",
      "目标价": "--",
      "EPS实际值(元)": "2.21(2025)",
      "T年度": "2026",
      "EPS预测": {
        "T年": "3.73",
        "T+1年": "4.88",
        "T+2年": "6.26"
      },
      "标题": "芯碁微装(688630)公司事件点评报告：公司业绩高增，AI算力驱动高端PCB与先进封装双轮放量",
      "研究机构": "华鑫证券"
    },
    {
      "序号": 15,
      "报告日期": "2026-03-17",
      "证券代码": "002916",
      "证券简称": "深南电路",
      "评级": "增持",
      "评级变化": "维持",
      "目标价": "--",
      "EPS实际值(元)": "4.91(2025)",
      "T年度": "2026",
      "EPS预测": {
        "T年": "7.84",
        "T+1年": "10.12",
        "T+2年": "13.08"
      },
      "标题": "深南电路(002916)业绩高增，AI算力及存储产品持续放量",
      "研究机构": "平安证券"
    },
    {
      "序号": 16,
      "报告日期": "2026-03-17",
      "证券代码": "600282",
      "证券简称": "南钢股份",
      "评级": "买入",
      "评级变化": "维持",
      "目标价": "--",
      "EPS实际值(元)": "0.4651(2025)",
      "T年度": "2026",
      "EPS预测": {
        "T年": "0.49",
        "T+1年": "0.52",
        "T+2年": "0.55"
      },
      "标题": "南钢股份(600282)归母净利润创四年新高",
      "研究机构": "国盛证券"
    },
    {
      "序号": 17,
      "报告日期": "2026-03-17",
      "证券代码": "600519",
      "证券简称": "贵州茅台",
      "评级": "买入",
      "评级变化": "维持",
      "目标价": "--",
      "EPS实际值(元)": "68.64(2024)",
      "T年度": "2025",
      "EPS预测": {
        "T年": "71.96",
        "T+1年": "71.98",
        "T+2年": "75.05"
      },
      "标题": "贵州茅台(600519)步入2C新时代，降维竞争持续成长",
      "研究机构": "东吴证券"
    },
    {
      "序号": 18,
      "报告日期": "2026-03-17",
      "证券代码": "688615",
      "证券简称": "合合信息",
      "评级": "买入",
      "评级变化": "维持",
      "目标价": "--",
      "EPS实际值(元)": "3.24(2025)",
      "T年度": "2026",
      "EPS预测": {
        "T年": "4.22",
        "T+1年": "5.40",
        "T+2年": "6.64"
      },
      "标题": "合合信息(688615)2025年报业绩景气高增，C端付费率提升驱动公司持续成长",
      "研究机构": "国盛证券"
    },
    {
      "序号": 19,
      "报告日期": "2026-03-17",
      "证券代码": "920069",
      "证券简称": "普昂医疗",
      "评级": "未知",
      "评级变化": "未知",
      "目标价": "--",
      "EPS实际值(元)": "1.53(2024)",
      "T年度": "2025",
      "EPS预测": {
        "T年": "--",
        "T+1年": "--",
        "T+2年": "--"
      },
      "标题": "普昂医疗(920069)胰岛素笔针全球份额领先，积极开拓微创介入类新产品",
      "研究机构": "华源证券"
    },
    {
      "序号": 20,
      "报告日期": "2026-03-17",
      "证券代码": "920689",
      "证券简称": "克莱特",
      "评级": "增持",
      "评级变化": "维持",
      "目标价": "--",
      "EPS实际值(元)": "0.7446(2024)",
      "T年度": "2025",
      "EPS预测": {
        "T年": "0.75",
        "T+1年": "1.00",
        "T+2年": "1.18"
      },
      "标题": "克莱特(920689)北交所信息更新：2亿可转债落地，智能风机扩产开启新篇章",
      "研究机构": "开源证券"
    }
  ]
}