{
  "获取时间": "2026-01-07 19:27:01",
  "数据日期": "2025-11-01",
  "数据条数": 208,
  "研报数据": [
    {
      "序号": 1,
      "报告日期": "2025-11-01",
      "证券代码": "603369",
      "证券简称": "今世缘",
      "评级": "买入",
      "评级变化": "维持",
      "目标价": "--",
      "EPS实际值(元)": "2.7365(2024)",
      "T年度": "2025",
      "EPS预测": {
        "T年": "2.22",
        "T+1年": "2.45",
        "T+2年": "2.73"
      },
      "标题": "今世缘(603369)2025年三季报点评：务实调整，重视渠道良性发展",
      "研究机构": "国联民生"
    },
    {
      "序号": 2,
      "报告日期": "2025-11-01",
      "证券代码": "002966",
      "证券简称": "苏州银行",
      "评级": "买入",
      "评级变化": "维持",
      "目标价": "--",
      "EPS实际值(元)": "1.31(2024)",
      "T年度": "2025",
      "EPS预测": {
        "T年": "1.15",
        "T+1年": "1.12",
        "T+2年": "1.25"
      },
      "标题": "苏州银行(002966)2025年三季报点评：息差回暖，资产质量保持优异",
      "研究机构": "东吴证券"
    },
    {
      "序号": 3,
      "报告日期": "2025-11-01",
      "证券代码": "603733",
      "证券简称": "仙鹤股份",
      "评级": "未知",
      "评级变化": "未知",
      "目标价": "--",
      "EPS实际值(元)": "1.42(2024)",
      "T年度": "2025",
      "EPS预测": {
        "T年": "1.57",
        "T+1年": "1.98",
        "T+2年": "2.45"
      },
      "标题": "仙鹤股份(603733)浆纸一体，成本优化，持续成长",
      "研究机构": "信达证券"
    },
    {
      "序号": 4,
      "报告日期": "2025-11-01",
      "证券代码": "300833",
      "证券简称": "浩洋股份",
      "评级": "买入",
      "评级变化": "维持",
      "目标价": "53.40",
      "EPS实际值(元)": "2.3851(2024)",
      "T年度": "2025",
      "EPS预测": {
        "T年": "1.96",
        "T+1年": "2.42",
        "T+2年": "2.98"
      },
      "标题": "浩洋股份(300833)利润拐点已现",
      "研究机构": "华泰证券"
    },
    {
      "序号": 5,
      "报告日期": "2025-11-01",
      "证券代码": "300857",
      "证券简称": "协创数据",
      "评级": "买入",
      "评级变化": "维持",
      "目标价": "--",
      "EPS实际值(元)": "2.83(2024)",
      "T年度": "2025",
      "EPS预测": {
        "T年": "3.42",
        "T+1年": "5.28",
        "T+2年": "7.44"
      },
      "标题": "协创数据(300857)2025年三季报点评：Q3业绩同比+25%，继续加码云算力布局",
      "研究机构": "国海证券"
    },
    {
      "序号": 6,
      "报告日期": "2025-11-01",
      "证券代码": "300979",
      "证券简称": "华利集团",
      "评级": "买入",
      "评级变化": "维持",
      "目标价": "--",
      "EPS实际值(元)": "3.29(2024)",
      "T年度": "2025",
      "EPS预测": {
        "T年": "2.92",
        "T+1年": "3.43",
        "T+2年": "4.02"
      },
      "标题": "华利集团(300979)2025年三季报点评：Q3营收波动，降本增效及新厂运营改善带来盈利拐点",
      "研究机构": "东吴证券"
    },
    {
      "序号": 7,
      "报告日期": "2025-11-01",
      "证券代码": "000651",
      "证券简称": "格力电器",
      "评级": "买入",
      "评级变化": "维持",
      "目标价": "--",
      "EPS实际值(元)": "5.83(2024)",
      "T年度": "2025",
      "EPS预测": {
        "T年": "5.60",
        "T+1年": "6.16",
        "T+2年": "6.79"
      },
      "标题": "格力电器(000651)空调基本盘的“盾”与多元化的“矛”",
      "研究机构": "申万宏源"
    },
    {
      "序号": 8,
      "报告日期": "2025-11-01",
      "证券代码": "002959",
      "证券简称": "小熊电器",
      "评级": "买入",
      "评级变化": "维持",
      "目标价": "--",
      "EPS实际值(元)": "1.8552(2024)",
      "T年度": "2025",
      "EPS预测": {
        "T年": "2.44",
        "T+1年": "2.87",
        "T+2年": "3.33"
      },
      "标题": "小熊电器(002959)2025Q3业绩端持续迅速修复，收入端逆势双位数增长",
      "研究机构": "太平洋证券"
    },
    {
      "序号": 9,
      "报告日期": "2025-11-01",
      "证券代码": "002966",
      "证券简称": "苏州银行",
      "评级": "买入",
      "评级变化": "维持",
      "目标价": "--",
      "EPS实际值(元)": "1.31(2024)",
      "T年度": "2025",
      "EPS预测": {
        "T年": "1.30",
        "T+1年": "1.35",
        "T+2年": "1.31"
      },
      "标题": "苏州银行(002966)2025年三季报点评：息差边际上升，存贷增速亮眼",
      "研究机构": "开源证券"
    },
    {
      "序号": 10,
      "报告日期": "2025-11-01",
      "证券代码": "600166",
      "证券简称": "福田汽车",
      "评级": "买入",
      "评级变化": "维持",
      "目标价": "--",
      "EPS实际值(元)": "0.01(2024)",
      "T年度": "2025",
      "EPS预测": {
        "T年": "0.19",
        "T+1年": "0.26",
        "T+2年": "0.27"
      },
      "标题": "福田汽车(600166)2025年三季报点评：Q3业绩同比高增，重卡出口增长强劲",
      "研究机构": "东吴证券"
    },
    {
      "序号": 11,
      "报告日期": "2025-11-01",
      "证券代码": "600459",
      "证券简称": "贵研铂业",
      "评级": "增持",
      "评级变化": "维持",
      "目标价": "25.69",
      "EPS实际值(元)": "0.77(2024)",
      "T年度": "2025",
      "EPS预测": {
        "T年": "0.92",
        "T+1年": "1.09",
        "T+2年": "1.26"
      },
      "标题": "贵研铂业(600459)Q3毛利率回升带动公司业绩增长",
      "研究机构": "华泰证券"
    },
    {
      "序号": 12,
      "报告日期": "2025-11-01",
      "证券代码": "001979",
      "证券简称": "招商蛇口",
      "评级": "买入",
      "评级变化": "维持",
      "目标价": "--",
      "EPS实际值(元)": "0.37(2024)",
      "T年度": "2025",
      "EPS预测": {
        "T年": "0.44",
        "T+1年": "0.47",
        "T+2年": "0.54"
      },
      "标题": "招商蛇口(001979)2025年三季报点评：深圳核心储备丰厚，2026年APEC峰会机遇难得",
      "研究机构": "光大证券"
    },
    {
      "序号": 13,
      "报告日期": "2025-11-01",
      "证券代码": "300740",
      "证券简称": "水羊股份",
      "评级": "买入",
      "评级变化": "维持",
      "目标价": "--",
      "EPS实际值(元)": "0.28(2024)",
      "T年度": "2025",
      "EPS预测": {
        "T年": "0.50",
        "T+1年": "0.72",
        "T+2年": "0.97"
      },
      "标题": "水羊股份(300740)公司信息更新报告：战略性投入致利润修复放缓，长期增长势能充足",
      "研究机构": "开源证券"
    },
    {
      "序号": 14,
      "报告日期": "2025-11-01",
      "证券代码": "600655",
      "证券简称": "豫园股份",
      "评级": "买入",
      "评级变化": "维持",
      "目标价": "6.50",
      "EPS实际值(元)": "0.032(2024)",
      "T年度": "2025",
      "EPS预测": {
        "T年": "0.06",
        "T+1年": "0.30",
        "T+2年": "0.36"
      },
      "标题": "豫园股份(600655)Q3物业开发业务对利润端有所拖累",
      "研究机构": "华泰证券"
    },
    {
      "序号": 15,
      "报告日期": "2025-11-01",
      "证券代码": "002216",
      "证券简称": "三全食品",
      "评级": "增持",
      "评级变化": "维持",
      "目标价": "--",
      "EPS实际值(元)": "0.62(2024)",
      "T年度": "2025",
      "EPS预测": {
        "T年": "0.65",
        "T+1年": "0.69",
        "T+2年": "0.74"
      },
      "标题": "三全食品(002216)2025年三季报点评：Q3收入降幅收窄，净利率有所改善",
      "研究机构": "光大证券"
    },
    {
      "序号": 16,
      "报告日期": "2025-11-01",
      "证券代码": "600863",
      "证券简称": "内蒙华电",
      "评级": "买入",
      "评级变化": "维持",
      "目标价": "4.93",
      "EPS实际值(元)": "0.34(2024)",
      "T年度": "2025",
      "EPS预测": {
        "T年": "0.36",
        "T+1年": "0.39",
        "T+2年": "0.42"
      },
      "标题": "内蒙华电(600863)期待煤炭热值修复带来盈利能力回升",
      "研究机构": "华泰证券"
    },
    {
      "序号": 17,
      "报告日期": "2025-11-01",
      "证券代码": "600933",
      "证券简称": "爱柯迪",
      "评级": "买入",
      "评级变化": "维持",
      "目标价": "30.50",
      "EPS实际值(元)": "0.98(2024)",
      "T年度": "2025",
      "EPS预测": {
        "T年": "1.22",
        "T+1年": "1.45",
        "T+2年": "1.69"
      },
      "标题": "爱柯迪(600933)盈利能力提升，机器人业务持续推进",
      "研究机构": "东方证券"
    },
    {
      "序号": 18,
      "报告日期": "2025-11-01",
      "证券代码": "002705",
      "证券简称": "新宝股份",
      "评级": "买入",
      "评级变化": "维持",
      "目标价": "--",
      "EPS实际值(元)": "1.2903(2024)",
      "T年度": "2025",
      "EPS预测": {
        "T年": "1.36",
        "T+1年": "1.49",
        "T+2年": "1.58"
      },
      "标题": "新宝股份(002705)2025年三季报点评：外销阶段性承压，毛利率费用率控制稳定",
      "研究机构": "申万宏源"
    },
    {
      "序号": 19,
      "报告日期": "2025-11-01",
      "证券代码": "601012",
      "证券简称": "隆基绿能",
      "评级": "买入",
      "评级变化": "维持",
      "目标价": "--",
      "EPS实际值(元)": "-1.14(2024)",
      "T年度": "2025",
      "EPS预测": {
        "T年": "-0.59",
        "T+1年": "0.41",
        "T+2年": "0.79"
      },
      "标题": "隆基绿能(601012)2025年三季报点评：Q3持续减亏，BC快速放量",
      "研究机构": "东吴证券"
    },
    {
      "序号": 20,
      "报告日期": "2025-11-01",
      "证券代码": "601155",
      "证券简称": "新城控股",
      "评级": "买入",
      "评级变化": "维持",
      "目标价": "18.90",
      "EPS实际值(元)": "0.33(2024)",
      "T年度": "2025",
      "EPS预测": {
        "T年": "0.37",
        "T+1年": "0.44",
        "T+2年": "0.53"
      },
      "标题": "新城控股(601155)平稳度过偿债高峰",
      "研究机构": "华泰证券"
    },
    {
      "序号": 21,
      "报告日期": "2025-11-01",
      "证券代码": "600025",
      "证券简称": "华能水电",
      "评级": "买入",
      "评级变化": "维持",
      "目标价": "--",
      "EPS实际值(元)": "0.44(2024)",
      "T年度": "2025",
      "EPS预测": {
        "T年": "0.47",
        "T+1年": "0.50",
        "T+2年": "0.51"
      },
      "标题": "华能水电(600025)2025年三季报点评：来水&装机对冲电价影响，定增落地、长期成长可期",
      "研究机构": "银河证券"
    },
    {
      "序号": 22,
      "报告日期": "2025-11-01",
      "证券代码": "002624",
      "证券简称": "完美世界",
      "评级": "买入",
      "评级变化": "维持",
      "目标价": "--",
      "EPS实际值(元)": "-0.68(2024)",
      "T年度": "2025",
      "EPS预测": {
        "T年": "0.41",
        "T+1年": "0.78",
        "T+2年": "0.92"
      },
      "标题": "完美世界(002624)利润端扭亏为盈，《异环》将为后续带来增量",
      "研究机构": "招商证券"
    },
    {
      "序号": 23,
      "报告日期": "2025-11-01",
      "证券代码": "002170",
      "证券简称": "芭田股份",
      "评级": "买入",
      "评级变化": "维持",
      "目标价": "--",
      "EPS实际值(元)": "0.4564(2024)",
      "T年度": "2025",
      "EPS预测": {
        "T年": "1.01",
        "T+1年": "1.22",
        "T+2年": "1.43"
      },
      "标题": "芭田股份(002170)Q3业绩环比回落，二期项目稳步推进中",
      "研究机构": "银河证券"
    },
    {
      "序号": 24,
      "报告日期": "2025-11-01",
      "证券代码": "601456",
      "证券简称": "国联民生",
      "评级": "买入",
      "评级变化": "维持",
      "目标价": "--",
      "EPS实际值(元)": "0.14(2024)",
      "T年度": "2025",
      "EPS预测": {
        "T年": "0.41",
        "T+1年": "0.40",
        "T+2年": "0.42"
      },
      "标题": "国联民生(601456)2025年三季报点评：并表民生证券叠加经纪、自营业务驱动，Q3利润延续高增",
      "研究机构": "东吴证券"
    },
    {
      "序号": 25,
      "报告日期": "2025-11-01",
      "证券代码": "600123",
      "证券简称": "兰花科创",
      "评级": "买入",
      "评级变化": "维持",
      "目标价": "--",
      "EPS实际值(元)": "0.4843(2024)",
      "T年度": "2025",
      "EPS预测": {
        "T年": "0.12",
        "T+1年": "0.30",
        "T+2年": "0.35"
      },
      "标题": "兰花科创(600123)公司信息更新报告：煤价下跌业绩承压，关注煤矿恢复及化工项目进展",
      "研究机构": "开源证券"
    },
    {
      "序号": 26,
      "报告日期": "2025-11-01",
      "证券代码": "688484",
      "证券简称": "南芯科技",
      "评级": "买入",
      "评级变化": "维持",
      "目标价": "--",
      "EPS实际值(元)": "0.72(2024)",
      "T年度": "2025",
      "EPS预测": {
        "T年": "0.64",
        "T+1年": "1.04",
        "T+2年": "1.56"
      },
      "标题": "南芯科技(688484)平台型成长逻辑兑现，三季度收入同环比增长显著",
      "研究机构": "长江证券"
    },
    {
      "序号": 27,
      "报告日期": "2025-11-01",
      "证券代码": "301061",
      "证券简称": "匠心家居",
      "评级": "买入",
      "评级变化": "维持",
      "目标价": "--",
      "EPS实际值(元)": "4.1(2024)",
      "T年度": "2025",
      "EPS预测": {
        "T年": "4.20",
        "T+1年": "5.42",
        "T+2年": "6.82"
      },
      "标题": "匠心家居(301061)2025年三季报点评：三季度业绩延续高增，客户结构持续优化",
      "研究机构": "光大证券"
    },
    {
      "序号": 28,
      "报告日期": "2025-11-01",
      "证券代码": "600132",
      "证券简称": "重庆啤酒",
      "评级": "增持",
      "评级变化": "维持",
      "目标价": "--",
      "EPS实际值(元)": "2.3(2024)",
      "T年度": "2025",
      "EPS预测": {
        "T年": "2.21",
        "T+1年": "2.32",
        "T+2年": "2.44"
      },
      "标题": "重庆啤酒(600132)公司信息更新报告：现金流良好，底部仍有支撑",
      "研究机构": "开源证券"
    },
    {
      "序号": 29,
      "报告日期": "2025-11-01",
      "证券代码": "600958",
      "证券简称": "东方证券",
      "评级": "买入",
      "评级变化": "维持",
      "目标价": "--",
      "EPS实际值(元)": "0.37(2024)",
      "T年度": "2025",
      "EPS预测": {
        "T年": "0.80",
        "T+1年": "1.00",
        "T+2年": "1.20"
      },
      "标题": "东方证券(600958)2025三季报点评：经纪、自营投资同比高增，基金AUM改善",
      "研究机构": "开源证券"
    },
    {
      "序号": 30,
      "报告日期": "2025-11-01",
      "证券代码": "600188",
      "证券简称": "兖矿能源",
      "评级": "买入",
      "评级变化": "维持",
      "目标价": "--",
      "EPS实际值(元)": "1.4574(2024)",
      "T年度": "2025",
      "EPS预测": {
        "T年": "1.09",
        "T+1年": "1.35",
        "T+2年": "1.57"
      },
      "标题": "兖矿能源(600188)公司信息更新报告：Q3业绩环比改善明显，成长性与高分红价值凸显",
      "研究机构": "开源证券"
    },
    {
      "序号": 31,
      "报告日期": "2025-11-01",
      "证券代码": "601211",
      "证券简称": "国泰海通",
      "评级": "买入",
      "评级变化": "维持",
      "目标价": "--",
      "EPS实际值(元)": "1.39(2024)",
      "T年度": "2025",
      "EPS预测": {
        "T年": "1.56",
        "T+1年": "1.50",
        "T+2年": "1.80"
      },
      "标题": "国泰海通(601211)2025三季报点评：业务全面增长驱动ROE高增，合并成效显现",
      "研究机构": "开源证券"
    },
    {
      "序号": 32,
      "报告日期": "2025-11-01",
      "证券代码": "601882",
      "证券简称": "海天精工",
      "评级": "买入",
      "评级变化": "维持",
      "目标价": "26.18",
      "EPS实际值(元)": "1(2024)",
      "T年度": "2025",
      "EPS预测": {
        "T年": "1.19",
        "T+1年": "1.33",
        "T+2年": "1.54"
      },
      "标题": "海天精工(601882)盈利能力承压，行业回暖复苏可期",
      "研究机构": "华泰证券"
    },
    {
      "序号": 33,
      "报告日期": "2025-11-01",
      "证券代码": "601577",
      "证券简称": "长沙银行",
      "评级": "买入",
      "评级变化": "维持",
      "目标价": "--",
      "EPS实际值(元)": "1.87(2024)",
      "T年度": "2025",
      "EPS预测": {
        "T年": "2.05",
        "T+1年": "2.16",
        "T+2年": "2.28"
      },
      "标题": "长沙银行(601577)2025年三季报点评：盈利保持韧性，关注率边际下降",
      "研究机构": "开源证券"
    },
    {
      "序号": 34,
      "报告日期": "2025-11-01",
      "证券代码": "603179",
      "证券简称": "新泉股份",
      "评级": "买入",
      "评级变化": "维持",
      "目标价": "91.35",
      "EPS实际值(元)": "2(2024)",
      "T年度": "2025",
      "EPS预测": {
        "T年": "2.03",
        "T+1年": "2.68",
        "T+2年": "3.42"
      },
      "标题": "新泉股份(603179)座椅及海外市场是增长点，拟设立子公司布局机器人业务",
      "研究机构": "东方证券"
    },
    {
      "序号": 35,
      "报告日期": "2025-11-01",
      "证券代码": "600258",
      "证券简称": "首旅酒店",
      "评级": "增持",
      "评级变化": "维持",
      "目标价": "--",
      "EPS实际值(元)": "0.7221(2024)",
      "T年度": "2025",
      "EPS预测": {
        "T年": "0.76",
        "T+1年": "0.87",
        "T+2年": "0.99"
      },
      "标题": "首旅酒店(600258)2025年三季报点评：25Q3RevPAR降幅环比收窄，经济型酒店韧性较强",
      "研究机构": "光大证券"
    },
    {
      "序号": 36,
      "报告日期": "2025-11-01",
      "证券代码": "603338",
      "证券简称": "浙江鼎力",
      "评级": "买入",
      "评级变化": "维持",
      "目标价": "--",
      "EPS实际值(元)": "3.22(2024)",
      "T年度": "2025",
      "EPS预测": {
        "T年": "4.08",
        "T+1年": "4.63",
        "T+2年": "5.65"
      },
      "标题": "浙江鼎力(603338)行业下行凸显韧性，有望受益于发达市场预期向上",
      "研究机构": "招商证券"
    },
    {
      "序号": 37,
      "报告日期": "2025-11-01",
      "证券代码": "601998",
      "证券简称": "中信银行",
      "评级": "买入",
      "评级变化": "维持",
      "目标价": "--",
      "EPS实际值(元)": "1.22(2024)",
      "T年度": "2025",
      "EPS预测": {
        "T年": "1.27",
        "T+1年": "1.31",
        "T+2年": "1.32"
      },
      "标题": "中信银行(601998)2025年三季报点评：单季息差环比提升，零售AUM高增",
      "研究机构": "开源证券"
    },
    {
      "序号": 38,
      "报告日期": "2025-11-01",
      "证券代码": "603727",
      "证券简称": "博迈科",
      "评级": "买入",
      "评级变化": "维持",
      "目标价": "16.51",
      "EPS实际值(元)": "0.36(2024)",
      "T年度": "2025",
      "EPS预测": {
        "T年": "0.32",
        "T+1年": "0.53",
        "T+2年": "1.17"
      },
      "标题": "博迈科(603727)新签FPSO订单有望贡献业绩增量",
      "研究机构": "华泰证券"
    },
    {
      "序号": 39,
      "报告日期": "2025-11-01",
      "证券代码": "603730",
      "证券简称": "岱美股份",
      "评级": "买入",
      "评级变化": "维持",
      "目标价": "9.02",
      "EPS实际值(元)": "0.49(2024)",
      "T年度": "2025",
      "EPS预测": {
        "T年": "0.41",
        "T+1年": "0.48",
        "T+2年": "0.56"
      },
      "标题": "岱美股份(603730)预计顶棚业务将贡献增量，有序扩产保障盈利增长",
      "研究机构": "东方证券"
    },
    {
      "序号": 40,
      "报告日期": "2025-11-01",
      "证券代码": "600741",
      "证券简称": "华域汽车",
      "评级": "买入",
      "评级变化": "维持",
      "目标价": "27.69",
      "EPS实际值(元)": "2.122(2024)",
      "T年度": "2025",
      "EPS预测": {
        "T年": "2.13",
        "T+1年": "2.28",
        "T+2年": "2.32"
      },
      "标题": "华域汽车(600741)盈利能力同环比改善，收购上汽清陶股权布局固态电池业务",
      "研究机构": "东方证券"
    },
    {
      "序号": 41,
      "报告日期": "2025-11-01",
      "证券代码": "600848",
      "证券简称": "上海临港",
      "评级": "买入",
      "评级变化": "维持",
      "目标价": "--",
      "EPS实际值(元)": "0.43(2024)",
      "T年度": "2025",
      "EPS预测": {
        "T年": "0.52",
        "T+1年": "0.53",
        "T+2年": "0.56"
      },
      "标题": "上海临港(600848)2025年三季报点评：产业生态集成运营，厚积薄发价值渐显",
      "研究机构": "光大证券"
    },
    {
      "序号": 42,
      "报告日期": "2025-11-01",
      "证券代码": "603801",
      "证券简称": "志邦家居",
      "评级": "增持",
      "评级变化": "维持",
      "目标价": "12.00",
      "EPS实际值(元)": "0.8896(2024)",
      "T年度": "2025",
      "EPS预测": {
        "T年": "0.66",
        "T+1年": "0.75",
        "T+2年": "0.81"
      },
      "标题": "志邦家居(603801)海外业务积极开拓贡献增长亮点",
      "研究机构": "华泰证券"
    },
    {
      "序号": 43,
      "报告日期": "2025-11-01",
      "证券代码": "603855",
      "证券简称": "华荣股份",
      "评级": "买入",
      "评级变化": "维持",
      "目标价": "30.00",
      "EPS实际值(元)": "1.37(2024)",
      "T年度": "2025",
      "EPS预测": {
        "T年": "1.40",
        "T+1年": "1.50",
        "T+2年": "1.75"
      },
      "标题": "华荣股份(603855)厂用防爆内需承压，外贸增长",
      "研究机构": "华泰证券"
    },
    {
      "序号": 44,
      "报告日期": "2025-11-01",
      "证券代码": "600926",
      "证券简称": "杭州银行",
      "评级": "买入",
      "评级变化": "维持",
      "目标价": "--",
      "EPS实际值(元)": "2.74(2024)",
      "T年度": "2025",
      "EPS预测": {
        "T年": "2.72",
        "T+1年": "3.18",
        "T+2年": "3.71"
      },
      "标题": "杭州银行(600926)2025年三季报点评：扩表速度环比提升，盈利增速维持高位",
      "研究机构": "光大证券"
    },
    {
      "序号": 45,
      "报告日期": "2025-11-01",
      "证券代码": "605337",
      "证券简称": "李子园",
      "评级": "增持",
      "评级变化": "维持",
      "目标价": "--",
      "EPS实际值(元)": "0.58(2024)",
      "T年度": "2025",
      "EPS预测": {
        "T年": "0.54",
        "T+1年": "0.59",
        "T+2年": "0.64"
      },
      "标题": "李子园(605337)公司信息更新报告：含乳饮料短期承压，电商渠道持续亮眼",
      "研究机构": "开源证券"
    },
    {
      "序号": 46,
      "报告日期": "2025-11-01",
      "证券代码": "601169",
      "证券简称": "北京银行",
      "评级": "买入",
      "评级变化": "维持",
      "目标价": "--",
      "EPS实际值(元)": "1.07(2024)",
      "T年度": "2025",
      "EPS预测": {
        "T年": "1.28",
        "T+1年": "1.33",
        "T+2年": "1.38"
      },
      "标题": "北京银行(601169)2025年三季报点评：扩表速度稳中有进，资产质量保持稳健",
      "研究机构": "光大证券"
    },
    {
      "序号": 47,
      "报告日期": "2025-11-01",
      "证券代码": "603997",
      "证券简称": "继峰股份",
      "评级": "买入",
      "评级变化": "维持",
      "目标价": "--",
      "EPS实际值(元)": "-0.46(2024)",
      "T年度": "2025",
      "EPS预测": {
        "T年": "0.32",
        "T+1年": "0.64",
        "T+2年": "0.91"
      },
      "标题": "继峰股份(603997)公司简评报告：2025Q3归母净利环比高增，乘用车座椅订单持续放量",
      "研究机构": "东海证券"
    },
    {
      "序号": 48,
      "报告日期": "2025-11-01",
      "证券代码": "605117",
      "证券简称": "德业股份",
      "评级": "买入",
      "评级变化": "维持",
      "目标价": "96.79",
      "EPS实际值(元)": "4.76(2024)",
      "T年度": "2025",
      "EPS预测": {
        "T年": "3.57",
        "T+1年": "4.45",
        "T+2年": "5.37"
      },
      "标题": "德业股份(605117)确收推迟等影响Q3利润释放",
      "研究机构": "华泰证券"
    },
    {
      "序号": 49,
      "报告日期": "2025-11-01",
      "证券代码": "601398",
      "证券简称": "工商银行",
      "评级": "买入",
      "评级变化": "维持",
      "目标价": "--",
      "EPS实际值(元)": "0.98(2024)",
      "T年度": "2025",
      "EPS预测": {
        "T年": "1.05",
        "T+1年": "1.08",
        "T+2年": "1.11"
      },
      "标题": "工商银行(601398)2025年三季报点评：盈利增速回正，资产质量稳健",
      "研究机构": "光大证券"
    },
    {
      "序号": 50,
      "报告日期": "2025-11-01",
      "证券代码": "601601",
      "证券简称": "中国太保",
      "评级": "买入",
      "评级变化": "维持",
      "目标价": "--",
      "EPS实际值(元)": "4.67(2024)",
      "T年度": "2025",
      "EPS预测": {
        "T年": "5.86",
        "T+1年": "6.63",
        "T+2年": "7.01"
      },
      "标题": "中国太保(601601)2025年三季报点评：NBV延续较好增长，投资驱动盈利增幅走阔",
      "研究机构": "光大证券"
    },
    {
      "序号": 51,
      "报告日期": "2025-11-01",
      "证券代码": "688526",
      "证券简称": "科前生物",
      "评级": "买入",
      "评级变化": "维持",
      "目标价": "--",
      "EPS实际值(元)": "0.82(2024)",
      "T年度": "2025",
      "EPS预测": {
        "T年": "1.03",
        "T+1年": "1.26",
        "T+2年": "1.51"
      },
      "标题": "科前生物(688526)公司信息更新报告：降本增效盈利向上，高研发投入驱动成长",
      "研究机构": "开源证券"
    },
    {
      "序号": 52,
      "报告日期": "2025-11-01",
      "证券代码": "601998",
      "证券简称": "中信银行",
      "评级": "增持",
      "评级变化": "维持",
      "目标价": "--",
      "EPS实际值(元)": "1.22(2024)",
      "T年度": "2025",
      "EPS预测": {
        "T年": "1.25",
        "T+1年": "1.29",
        "T+2年": "1.33"
      },
      "标题": "中信银行(601998)2025年三季报点评：净息差季环比持平，盈利增速稳中略升",
      "研究机构": "光大证券"
    },
    {
      "序号": 53,
      "报告日期": "2025-11-01",
      "证券代码": "688696",
      "证券简称": "极米科技",
      "评级": "买入",
      "评级变化": "维持",
      "目标价": "--",
      "EPS实际值(元)": "1.75(2024)",
      "T年度": "2025",
      "EPS预测": {
        "T年": "3.10",
        "T+1年": "3.79",
        "T+2年": "4.41"
      },
      "标题": "极米科技(688696)2025Q3利润端大幅减亏，盈利能力显著提升",
      "研究机构": "太平洋证券"
    },
    {
      "序号": 54,
      "报告日期": "2025-11-01",
      "证券代码": "688222",
      "证券简称": "成都先导",
      "评级": "买入",
      "评级变化": "维持",
      "目标价": "--",
      "EPS实际值(元)": "0.13(2024)",
      "T年度": "2025",
      "EPS预测": {
        "T年": "0.26",
        "T+1年": "0.33",
        "T+2年": "0.42"
      },
      "标题": "成都先导(688222)业绩超预期，主业持续恢复",
      "研究机构": "中泰证券"
    },
    {
      "序号": 55,
      "报告日期": "2025-11-01",
      "证券代码": "603369",
      "证券简称": "今世缘",
      "评级": "增持",
      "评级变化": "维持",
      "目标价": "50.00",
      "EPS实际值(元)": "2.7365(2024)",
      "T年度": "2025",
      "EPS预测": {
        "T年": "--",
        "T+1年": "--",
        "T+2年": "--"
      },
      "标题": "今世缘(603369)3Q25业绩符合预期，报表延续释放压力",
      "研究机构": "中金公司"
    },
    {
      "序号": 56,
      "报告日期": "2025-11-01",
      "证券代码": "920118",
      "证券简称": "太湖远大",
      "评级": "增持",
      "评级变化": "维持",
      "目标价": "--",
      "EPS实际值(元)": "1.5319(2024)",
      "T年度": "2025",
      "EPS预测": {
        "T年": "0.62",
        "T+1年": "1.49",
        "T+2年": "1.97"
      },
      "标题": "太湖远大(920118)北交所信息更新：需求减少致公司业绩承压，超高压线缆料产品值得期待",
      "研究机构": "开源证券"
    },
    {
      "序号": 57,
      "报告日期": "2025-11-01",
      "证券代码": "920160",
      "证券简称": "北矿检测",
      "评级": "未知",
      "评级变化": "未知",
      "目标价": "--",
      "EPS实际值(元)": "0.65(2024)",
      "T年度": "2025",
      "EPS预测": {
        "T年": "--",
        "T+1年": "--",
        "T+2年": "--"
      },
      "标题": "北矿检测(920160)北交所新股申购报告：有色检测小巨人市占第一，LME牌照+技术壁垒铸就优势",
      "研究机构": "开源证券"
    },
    {
      "序号": 58,
      "报告日期": "2025-11-01",
      "证券代码": "603808",
      "证券简称": "歌力思",
      "评级": "增持",
      "评级变化": "维持",
      "目标价": "--",
      "EPS实际值(元)": "-0.85(2024)",
      "T年度": "2025",
      "EPS预测": {
        "T年": "0.46",
        "T+1年": "0.57",
        "T+2年": "0.62"
      },
      "标题": "歌力思(603808)单三季度国内市场增长9%25，利润同比大幅改善",
      "研究机构": "申万宏源"
    },
    {
      "序号": 59,
      "报告日期": "2025-11-01",
      "证券代码": "920489",
      "证券简称": "佳先股份",
      "评级": "增持",
      "评级变化": "维持",
      "目标价": "--",
      "EPS实际值(元)": "0.09(2024)",
      "T年度": "2025",
      "EPS预测": {
        "T年": "0.10",
        "T+1年": "0.29",
        "T+2年": "0.44"
      },
      "标题": "佳先股份(920489)北交所信息更新：二期光刻胶原料项目建设加速，聚焦高端电子材料领域打开第二增长曲线",
      "研究机构": "开源证券"
    },
    {
      "序号": 60,
      "报告日期": "2025-11-01",
      "证券代码": "688516",
      "证券简称": "奥特维",
      "评级": "买入",
      "评级变化": "维持",
      "目标价": "58.00",
      "EPS实际值(元)": "4.05(2024)",
      "T年度": "2025",
      "EPS预测": {
        "T年": "2.00",
        "T+1年": "2.13",
        "T+2年": "2.51"
      },
      "标题": "奥特维(688516)加码多分片串焊机研发",
      "研究机构": "华泰证券"
    },
    {
      "序号": 61,
      "报告日期": "2025-11-01",
      "证券代码": "000157",
      "证券简称": "中联重科",
      "评级": "买入",
      "评级变化": "维持",
      "目标价": "--",
      "EPS实际值(元)": "0.41(2024)",
      "T年度": "2025",
      "EPS预测": {
        "T年": "0.58",
        "T+1年": "0.73",
        "T+2年": "0.87"
      },
      "标题": "中联重科(000157)业绩高增，内外销共振",
      "研究机构": "华西证券"
    },
    {
      "序号": 62,
      "报告日期": "2025-11-01",
      "证券代码": "601111",
      "证券简称": "中国国航",
      "评级": "增持",
      "评级变化": "维持",
      "目标价": "--",
      "EPS实际值(元)": "-0.01(2024)",
      "T年度": "2025",
      "EPS预测": {
        "T年": "0.07",
        "T+1年": "0.37",
        "T+2年": "0.49"
      },
      "标题": "中国国航(601111)2025年三季报点评：盈利能力待修复，关注出行景气度回升",
      "研究机构": "信达证券"
    },
    {
      "序号": 63,
      "报告日期": "2025-11-01",
      "证券代码": "920029",
      "证券简称": "开发科技",
      "评级": "增持",
      "评级变化": "维持",
      "目标价": "--",
      "EPS实际值(元)": "5.87(2024)",
      "T年度": "2025",
      "EPS预测": {
        "T年": "5.25",
        "T+1年": "6.17",
        "T+2年": "7.03"
      },
      "标题": "开发科技(920029)2025三季报点评：部分订单延期致Q3业绩环比下滑，看好电表境内外双市场拓展潜力",
      "研究机构": "东吴证券"
    },
    {
      "序号": 64,
      "报告日期": "2025-11-01",
      "证券代码": "920418",
      "证券简称": "苏轴股份",
      "评级": "买入",
      "评级变化": "维持",
      "目标价": "--",
      "EPS实际值(元)": "1.11(2024)",
      "T年度": "2025",
      "EPS预测": {
        "T年": "1.19",
        "T+1年": "1.49",
        "T+2年": "1.85"
      },
      "标题": "苏轴股份(920418)2025三季报点评：客户收入确认延后及降价致利润率下滑，看好机器人等新兴赛道增量",
      "研究机构": "东吴证券"
    },
    {
      "序号": 65,
      "报告日期": "2025-11-01",
      "证券代码": "920806",
      "证券简称": "云星宇",
      "评级": "增持",
      "评级变化": "调低",
      "目标价": "--",
      "EPS实际值(元)": "0.4(2024)",
      "T年度": "2025",
      "EPS预测": {
        "T年": "0.29",
        "T+1年": "0.39",
        "T+2年": "0.43"
      },
      "标题": "云星宇(920806)2025年三季报点评：项目结算进度问题致业绩不达预期，长期发展动能犹在",
      "研究机构": "东吴证券"
    },
    {
      "序号": 66,
      "报告日期": "2025-11-01",
      "证券代码": "920978",
      "证券简称": "开特股份",
      "评级": "买入",
      "评级变化": "维持",
      "目标价": "--",
      "EPS实际值(元)": "0.78(2024)",
      "T年度": "2025",
      "EPS预测": {
        "T年": "0.99",
        "T+1年": "1.33",
        "T+2年": "1.72"
      },
      "标题": "开特股份(920978)2025三季报点评：汽车市场良好发展带动公司产品稳步增长，25Q1-3业绩同比+37%",
      "研究机构": "东吴证券"
    },
    {
      "序号": 67,
      "报告日期": "2025-11-01",
      "证券代码": "000568",
      "证券简称": "泸州老窖",
      "评级": "买入",
      "评级变化": "维持",
      "目标价": "--",
      "EPS实际值(元)": "9.18(2024)",
      "T年度": "2025",
      "EPS预测": {
        "T年": "7.74",
        "T+1年": "8.03",
        "T+2年": "8.54"
      },
      "标题": "泸州老窖(000568)2025年三季报点评：报表端继续调整，中档及大众产品相对较优",
      "研究机构": "光大证券"
    },
    {
      "序号": 68,
      "报告日期": "2025-11-01",
      "证券代码": "002465",
      "证券简称": "海格通信",
      "评级": "买入",
      "评级变化": "维持",
      "目标价": "--",
      "EPS实际值(元)": "0.02(2024)",
      "T年度": "2025",
      "EPS预测": {
        "T年": "-0.08",
        "T+1年": "0.14",
        "T+2年": "0.20"
      },
      "标题": "海格通信(002465)下游客户订单延缓，业绩由盈转亏",
      "研究机构": "华西证券"
    },
    {
      "序号": 69,
      "报告日期": "2025-11-01",
      "证券代码": "920242",
      "证券简称": "建邦科技",
      "评级": "买入",
      "评级变化": "维持",
      "目标价": "--",
      "EPS实际值(元)": "1.65(2024)",
      "T年度": "2025",
      "EPS预测": {
        "T年": "1.51",
        "T+1年": "2.22",
        "T+2年": "2.62"
      },
      "标题": "建邦科技(920242)坏账计提致Q3业绩短期承压，关注泰国工厂26年产能弹性",
      "研究机构": "申万宏源"
    },
    {
      "序号": 70,
      "报告日期": "2025-11-01",
      "证券代码": "000858",
      "证券简称": "五 粮 液",
      "评级": "买入",
      "评级变化": "维持",
      "目标价": "--",
      "EPS实际值(元)": "8.2062(2024)",
      "T年度": "2025",
      "EPS预测": {
        "T年": "6.75",
        "T+1年": "6.79",
        "T+2年": "7.17"
      },
      "标题": "五粮液(000858)2025年三季报点评：卸下包袱，大幅出清",
      "研究机构": "光大证券"
    },
    {
      "序号": 71,
      "报告日期": "2025-11-01",
      "证券代码": "000651",
      "证券简称": "格力电器",
      "评级": "买入",
      "评级变化": "维持",
      "目标价": "50.60",
      "EPS实际值(元)": "5.83(2024)",
      "T年度": "2025",
      "EPS预测": {
        "T年": "5.62",
        "T+1年": "5.93",
        "T+2年": "6.29"
      },
      "标题": "格力电器(000651)经营阶段承压，中期分红增强股东回报",
      "研究机构": "国投证券"
    },
    {
      "序号": 72,
      "报告日期": "2025-11-01",
      "证券代码": "000858",
      "证券简称": "五 粮 液",
      "评级": "增持",
      "评级变化": "维持",
      "目标价": "--",
      "EPS实际值(元)": "8.2062(2024)",
      "T年度": "2025",
      "EPS预测": {
        "T年": "6.03",
        "T+1年": "6.42",
        "T+2年": "7.05"
      },
      "标题": "五粮液(000858)主动调整出清，静待破局改善",
      "研究机构": "财通证券"
    },
    {
      "序号": 73,
      "报告日期": "2025-11-01",
      "证券代码": "000799",
      "证券简称": "酒鬼酒",
      "评级": "增持",
      "评级变化": "维持",
      "目标价": "70.40",
      "EPS实际值(元)": "0.0384(2024)",
      "T年度": "2025",
      "EPS预测": {
        "T年": "0.14",
        "T+1年": "0.56",
        "T+2年": "0.88"
      },
      "标题": "酒鬼酒(000799)持续调整，期待胖东来新品贡献增量",
      "研究机构": "华泰证券"
    },
    {
      "序号": 74,
      "报告日期": "2025-11-01",
      "证券代码": "000969",
      "证券简称": "安泰科技",
      "评级": "买入",
      "评级变化": "维持",
      "目标价": "--",
      "EPS实际值(元)": "0.361(2024)",
      "T年度": "2025",
      "EPS预测": {
        "T年": "0.32",
        "T+1年": "0.37",
        "T+2年": "0.47"
      },
      "标题": "安泰科技(000969)2025年三季报点评：前三季度扣非归母净利润稳健增长，聚焦主业未来可期",
      "研究机构": "国海证券"
    },
    {
      "序号": 75,
      "报告日期": "2025-11-01",
      "证券代码": "000998",
      "证券简称": "隆平高科",
      "评级": "买入",
      "评级变化": "维持",
      "目标价": "--",
      "EPS实际值(元)": "0.09(2024)",
      "T年度": "2025",
      "EPS预测": {
        "T年": "0.22",
        "T+1年": "0.40",
        "T+2年": "0.57"
      },
      "标题": "隆平高科(000998)逆势减亏彰显经营韧性，优质品种护航粮食安全",
      "研究机构": "招商证券"
    },
    {
      "序号": 76,
      "报告日期": "2025-11-01",
      "证券代码": "000998",
      "证券简称": "隆平高科",
      "评级": "增持",
      "评级变化": "维持",
      "目标价": "--",
      "EPS实际值(元)": "0.09(2024)",
      "T年度": "2025",
      "EPS预测": {
        "T年": "0.15",
        "T+1年": "0.36",
        "T+2年": "0.48"
      },
      "标题": "隆平高科(000998)2025三季报点评：市场拓展、降本增效并进，海外经营同比好转",
      "研究机构": "国信证券"
    },
    {
      "序号": 77,
      "报告日期": "2025-11-01",
      "证券代码": "001323",
      "证券简称": "慕思股份",
      "评级": "买入",
      "评级变化": "维持",
      "目标价": "--",
      "EPS实际值(元)": "1.95(2024)",
      "T年度": "2025",
      "EPS预测": {
        "T年": "1.64",
        "T+1年": "1.77",
        "T+2年": "1.90"
      },
      "标题": "慕思股份(001323)Q3营收修复，营销投入蓄势长期发展",
      "研究机构": "华福证券"
    },
    {
      "序号": 78,
      "报告日期": "2025-11-01",
      "证券代码": "002041",
      "证券简称": "登海种业",
      "评级": "增持",
      "评级变化": "维持",
      "目标价": "--",
      "EPS实际值(元)": "0.0643(2024)",
      "T年度": "2025",
      "EPS预测": {
        "T年": "0.09",
        "T+1年": "0.12",
        "T+2年": "0.16"
      },
      "标题": "登海种业(002041)2025三季报点评：玉米种业短期景气低迷，Q3末合同负债同比-11%",
      "研究机构": "国信证券"
    },
    {
      "序号": 79,
      "报告日期": "2025-11-01",
      "证券代码": "002572",
      "证券简称": "索菲亚",
      "评级": "未知",
      "评级变化": "未知",
      "目标价": "--",
      "EPS实际值(元)": "1.43(2024)",
      "T年度": "2025",
      "EPS预测": {
        "T年": "0.96",
        "T+1年": "1.11",
        "T+2年": "1.25"
      },
      "标题": "索菲亚(002572)多品牌、全方位布局，逆势毛利率提升",
      "研究机构": "信达证券"
    },
    {
      "序号": 80,
      "报告日期": "2025-11-01",
      "证券代码": "002938",
      "证券简称": "鹏鼎控股",
      "评级": "买入",
      "评级变化": "维持",
      "目标价": "--",
      "EPS实际值(元)": "1.56(2024)",
      "T年度": "2025",
      "EPS预测": {
        "T年": "1.89",
        "T+1年": "2.55",
        "T+2年": "3.03"
      },
      "标题": "鹏鼎控股(002938)各业务板块稳定增长，AI+PCB产能释放可期",
      "研究机构": "国盛证券"
    },
    {
      "序号": 81,
      "报告日期": "2025-11-01",
      "证券代码": "002129",
      "证券简称": "TCL中环",
      "评级": "买入",
      "评级变化": "维持",
      "目标价": "11.01",
      "EPS实际值(元)": "-2.4629(2024)",
      "T年度": "2025",
      "EPS预测": {
        "T年": "-1.76",
        "T+1年": "0.28",
        "T+2年": "0.63"
      },
      "标题": "TCL中环(002129)反内卷驱动亏损大幅收窄",
      "研究机构": "华泰证券"
    },
    {
      "序号": 82,
      "报告日期": "2025-11-01",
      "证券代码": "002304",
      "证券简称": "洋河股份",
      "评级": "增持",
      "评级变化": "维持",
      "目标价": "--",
      "EPS实际值(元)": "4.4299(2024)",
      "T年度": "2025",
      "EPS预测": {
        "T年": "2.21",
        "T+1年": "2.73",
        "T+2年": "3.00"
      },
      "标题": "洋河股份(002304)秩序逐步恢复，期待积极变革",
      "研究机构": "招商证券"
    },
    {
      "序号": 83,
      "报告日期": "2025-11-01",
      "证券代码": "603801",
      "证券简称": "志邦家居",
      "评级": "未知",
      "评级变化": "未知",
      "目标价": "--",
      "EPS实际值(元)": "0.8896(2024)",
      "T年度": "2025",
      "EPS预测": {
        "T年": "0.58",
        "T+1年": "0.69",
        "T+2年": "0.80"
      },
      "标题": "志邦家居(603801)大宗持续收缩，零售聚焦整家，海外加速发展",
      "研究机构": "信达证券"
    },
    {
      "序号": 84,
      "报告日期": "2025-11-01",
      "证券代码": "300442",
      "证券简称": "润泽科技",
      "评级": "买入",
      "评级变化": "维持",
      "目标价": "66.28",
      "EPS实际值(元)": "1.04(2024)",
      "T年度": "2025",
      "EPS预测": {
        "T年": "3.24",
        "T+1年": "1.85",
        "T+2年": "2.35"
      },
      "标题": "润泽科技(300442)REITS项目发行增厚股权处置收益",
      "研究机构": "华泰证券"
    },
    {
      "序号": 85,
      "报告日期": "2025-11-01",
      "证券代码": "603833",
      "证券简称": "欧派家居",
      "评级": "未知",
      "评级变化": "未知",
      "目标价": "--",
      "EPS实际值(元)": "4.29(2024)",
      "T年度": "2025",
      "EPS预测": {
        "T年": "4.08",
        "T+1年": "4.42",
        "T+2年": "4.77"
      },
      "标题": "欧派家居(603833)稳中求进，逆势变革，长期突破",
      "研究机构": "信达证券"
    },
    {
      "序号": 86,
      "报告日期": "2025-11-01",
      "证券代码": "600004",
      "证券简称": "白云机场",
      "评级": "增持",
      "评级变化": "维持",
      "目标价": "10.90",
      "EPS实际值(元)": "0.39(2024)",
      "T年度": "2025",
      "EPS预测": {
        "T年": "0.58",
        "T+1年": "0.40",
        "T+2年": "0.47"
      },
      "标题": "白云机场(600004)关注T3投产对短期盈利的影响",
      "研究机构": "华泰证券"
    },
    {
      "序号": 87,
      "报告日期": "2025-11-01",
      "证券代码": "002458",
      "证券简称": "益生股份",
      "评级": "增持",
      "评级变化": "维持",
      "目标价": "--",
      "EPS实际值(元)": "0.46(2024)",
      "T年度": "2025",
      "EPS预测": {
        "T年": "0.20",
        "T+1年": "0.48",
        "T+2年": "0.54"
      },
      "标题": "益生股份(002458)2025三季报点评：受益旺季行情回暖，Q3归母净利润环比+33%",
      "研究机构": "国信证券"
    },
    {
      "序号": 88,
      "报告日期": "2025-11-01",
      "证券代码": "600009",
      "证券简称": "上海机场",
      "评级": "增持",
      "评级变化": "维持",
      "目标价": "36.60",
      "EPS实际值(元)": "0.78(2024)",
      "T年度": "2025",
      "EPS预测": {
        "T年": "0.89",
        "T+1年": "1.08",
        "T+2年": "1.24"
      },
      "标题": "上海机场(600009)流量增长%2b经营杠杆推动盈利高增",
      "研究机构": "华泰证券"
    },
    {
      "序号": 89,
      "报告日期": "2025-11-01",
      "证券代码": "600601",
      "证券简称": "方正科技",
      "评级": "买入",
      "评级变化": "维持",
      "目标价": "--",
      "EPS实际值(元)": "0.06(2024)",
      "T年度": "2025",
      "EPS预测": {
        "T年": "0.11",
        "T+1年": "0.18",
        "T+2年": "0.25"
      },
      "标题": "方正科技(600601)2025年三季报点评：业绩环比高增，AI助力成长",
      "研究机构": "长江证券"
    },
    {
      "序号": 90,
      "报告日期": "2025-11-01",
      "证券代码": "600690",
      "证券简称": "海尔智家",
      "评级": "买入",
      "评级变化": "维持",
      "目标价": "31.54",
      "EPS实际值(元)": "2.02(2024)",
      "T年度": "2025",
      "EPS预测": {
        "T年": "2.27",
        "T+1年": "2.53",
        "T+2年": "2.79"
      },
      "标题": "海尔智家(600690)Q3内销增长提速，外销稳步提升，数字化变革成效持续凸显",
      "研究机构": "国投证券"
    },
    {
      "序号": 91,
      "报告日期": "2025-11-01",
      "证券代码": "600820",
      "证券简称": "隧道股份",
      "评级": "买入",
      "评级变化": "维持",
      "目标价": "10.30",
      "EPS实际值(元)": "0.9(2024)",
      "T年度": "2025",
      "EPS预测": {
        "T年": "0.95",
        "T+1年": "0.99",
        "T+2年": "1.04"
      },
      "标题": "隧道股份(600820)Q4投资收益影响有望减弱",
      "研究机构": "华泰证券"
    },
    {
      "序号": 92,
      "报告日期": "2025-11-01",
      "证券代码": "000596",
      "证券简称": "古井贡酒",
      "评级": "增持",
      "评级变化": "维持",
      "目标价": "--",
      "EPS实际值(元)": "10.44(2024)",
      "T年度": "2025",
      "EPS预测": {
        "T年": "8.34",
        "T+1年": "8.67",
        "T+2年": "9.59"
      },
      "标题": "古井贡酒(000596)三季度去化库存，报表端释放压力",
      "研究机构": "太平洋证券"
    },
    {
      "序号": 93,
      "报告日期": "2025-11-01",
      "证券代码": "002938",
      "证券简称": "鹏鼎控股",
      "评级": "买入",
      "评级变化": "维持",
      "目标价": "--",
      "EPS实际值(元)": "1.56(2024)",
      "T年度": "2025",
      "EPS预测": {
        "T年": "1.77",
        "T+1年": "2.31",
        "T+2年": "3.04"
      },
      "标题": "鹏鼎控股(002938)Q3业绩下滑受折旧、费用拖累，AI算力客户及产能拓展顺利",
      "研究机构": "招商证券"
    },
    {
      "序号": 94,
      "报告日期": "2025-11-01",
      "证券代码": "601200",
      "证券简称": "上海环境",
      "评级": "买入",
      "评级变化": "维持",
      "目标价": "9.57",
      "EPS实际值(元)": "0.4274(2024)",
      "T年度": "2025",
      "EPS预测": {
        "T年": "0.44",
        "T+1年": "0.46",
        "T+2年": "0.49"
      },
      "标题": "上海环境(601200)业绩符合预期，上网电量稳健增长",
      "研究机构": "华泰证券"
    },
    {
      "序号": 95,
      "报告日期": "2025-11-01",
      "证券代码": "300487",
      "证券简称": "蓝晓科技",
      "评级": "买入",
      "评级变化": "维持",
      "目标价": "--",
      "EPS实际值(元)": "1.56(2024)",
      "T年度": "2025",
      "EPS预测": {
        "T年": "1.77",
        "T+1年": "2.15",
        "T+2年": "2.77"
      },
      "标题": "蓝晓科技(300487)公司跟踪报告：战略聚焦高附加值，生科布局再次加码",
      "研究机构": "方正证券"
    },
    {
      "序号": 96,
      "报告日期": "2025-11-01",
      "证券代码": "601778",
      "证券简称": "晶科科技",
      "评级": "买入",
      "评级变化": "调高",
      "目标价": "5.20",
      "EPS实际值(元)": "0.09(2024)",
      "T年度": "2025",
      "EPS预测": {
        "T年": "0.17",
        "T+1年": "0.20",
        "T+2年": "0.23"
      },
      "标题": "晶科科技(601778)海外项目与储能增长展现潜在价值",
      "研究机构": "华泰证券"
    },
    {
      "序号": 97,
      "报告日期": "2025-11-01",
      "证券代码": "601998",
      "证券简称": "中信银行",
      "评级": "增持",
      "评级变化": "维持",
      "目标价": "--",
      "EPS实际值(元)": "1.22(2024)",
      "T年度": "2025",
      "EPS预测": {
        "T年": "1.17",
        "T+1年": "1.20",
        "T+2年": "1.29"
      },
      "标题": "中信银行(601998)详解中信银行2025三季报：息差企稳回升，利润增长稳健",
      "研究机构": "中泰证券"
    },
    {
      "序号": 98,
      "报告日期": "2025-11-01",
      "证券代码": "300740",
      "证券简称": "水羊股份",
      "评级": "买入",
      "评级变化": "维持",
      "目标价": "--",
      "EPS实际值(元)": "0.28(2024)",
      "T年度": "2025",
      "EPS预测": {
        "T年": "0.55",
        "T+1年": "0.82",
        "T+2年": "1.09"
      },
      "标题": "水羊股份(300740)2025年三季报点评：研发投入加码，持续推进高奢品牌矩阵建设",
      "研究机构": "国联民生"
    },
    {
      "序号": 99,
      "报告日期": "2025-11-01",
      "证券代码": "603056",
      "证券简称": "德邦股份",
      "评级": "中性",
      "评级变化": "维持",
      "目标价": "12.86",
      "EPS实际值(元)": "0.85(2024)",
      "T年度": "2025",
      "EPS预测": {
        "T年": "-0.34",
        "T+1年": "0.92",
        "T+2年": "1.24"
      },
      "标题": "德邦股份(603056)主动聚焦核心产品，业绩阶段性承压",
      "研究机构": "华泰证券"
    },
    {
      "序号": 100,
      "报告日期": "2025-11-01",
      "证券代码": "301269",
      "证券简称": "华大九天",
      "评级": "增持",
      "评级变化": "维持",
      "目标价": "--",
      "EPS实际值(元)": "0.2(2024)",
      "T年度": "2025",
      "EPS预测": {
        "T年": "0.19",
        "T+1年": "0.35",
        "T+2年": "0.52"
      },
      "标题": "华大九天(301269)营收增速阶段性放缓，产品布局不断完善",
      "研究机构": "中泰证券"
    },
    {
      "序号": 101,
      "报告日期": "2025-11-01",
      "证券代码": "600221",
      "证券简称": "海航控股",
      "评级": "增持",
      "评级变化": "维持",
      "目标价": "--",
      "EPS实际值(元)": "-0.021(2024)",
      "T年度": "2025",
      "EPS预测": {
        "T年": "0.05",
        "T+1年": "0.09",
        "T+2年": "0.14"
      },
      "标题": "海航控股(600221)国际运力同比大幅增长，前三季度盈利显著改善",
      "研究机构": "中泰证券"
    },
    {
      "序号": 102,
      "报告日期": "2025-11-01",
      "证券代码": "603587",
      "证券简称": "地素时尚",
      "评级": "买入",
      "评级变化": "维持",
      "目标价": "--",
      "EPS实际值(元)": "0.65(2024)",
      "T年度": "2025",
      "EPS预测": {
        "T年": "0.59",
        "T+1年": "0.71",
        "T+2年": "0.80"
      },
      "标题": "地素时尚(603587)2025Q3利润转正增长，核心品牌毛利率坚挺",
      "研究机构": "国盛证券"
    },
    {
      "序号": 103,
      "报告日期": "2025-11-01",
      "证券代码": "000776",
      "证券简称": "广发证券",
      "评级": "买入",
      "评级变化": "维持",
      "目标价": "--",
      "EPS实际值(元)": "1.15(2024)",
      "T年度": "2025",
      "EPS预测": {
        "T年": "1.71",
        "T+1年": "1.95",
        "T+2年": "2.19"
      },
      "标题": "广发证券(000776)25Q3点评：净利润增62%25，经纪、投资带动增长",
      "研究机构": "中泰证券"
    },
    {
      "序号": 104,
      "报告日期": "2025-11-01",
      "证券代码": "600406",
      "证券简称": "国电南瑞",
      "评级": "买入",
      "评级变化": "维持",
      "目标价": "--",
      "EPS实际值(元)": "0.95(2024)",
      "T年度": "2025",
      "EPS预测": {
        "T年": "1.02",
        "T+1年": "1.16",
        "T+2年": "1.32"
      },
      "标题": "国电南瑞(600406)2025年三季报点评：业绩稳步增长，费用率持续压降",
      "研究机构": "国联民生"
    },
    {
      "序号": 105,
      "报告日期": "2025-11-01",
      "证券代码": "600499",
      "证券简称": "科达制造",
      "评级": "增持",
      "评级变化": "维持",
      "目标价": "--",
      "EPS实际值(元)": "0.534(2024)",
      "T年度": "2025",
      "EPS预测": {
        "T年": "0.82",
        "T+1年": "0.97",
        "T+2年": "1.06"
      },
      "标题": "科达制造(600499)2025年三季报点评：产能释放推动业绩增长，25Q3现金流改善明显",
      "研究机构": "光大证券"
    },
    {
      "序号": 106,
      "报告日期": "2025-11-01",
      "证券代码": "001328",
      "证券简称": "登康口腔",
      "评级": "增持",
      "评级变化": "维持",
      "目标价": "--",
      "EPS实际值(元)": "0.94(2024)",
      "T年度": "2025",
      "EPS预测": {
        "T年": "1.10",
        "T+1年": "1.38",
        "T+2年": "1.68"
      },
      "标题": "登康口腔(001328)积极优化运营策略",
      "研究机构": "天风证券"
    },
    {
      "序号": 107,
      "报告日期": "2025-11-01",
      "证券代码": "603808",
      "证券简称": "歌力思",
      "评级": "增持",
      "评级变化": "维持",
      "目标价": "--",
      "EPS实际值(元)": "-0.85(2024)",
      "T年度": "2025",
      "EPS预测": {
        "T年": "0.47",
        "T+1年": "0.62",
        "T+2年": "0.73"
      },
      "标题": "歌力思(603808)海外同比减亏，国内业务高质量增长",
      "研究机构": "国盛证券"
    },
    {
      "序号": 108,
      "报告日期": "2025-11-01",
      "证券代码": "600519",
      "证券简称": "贵州茅台",
      "评级": "买入",
      "评级变化": "维持",
      "目标价": "--",
      "EPS实际值(元)": "68.64(2024)",
      "T年度": "2025",
      "EPS预测": {
        "T年": "75.03",
        "T+1年": "81.27",
        "T+2年": "87.86"
      },
      "标题": "贵州茅台(600519)三季度理性降速，茅台酒稳定增长",
      "研究机构": "中泰证券"
    },
    {
      "序号": 109,
      "报告日期": "2025-11-01",
      "证券代码": "603885",
      "证券简称": "吉祥航空",
      "评级": "买入",
      "评级变化": "维持",
      "目标价": "--",
      "EPS实际值(元)": "0.42(2024)",
      "T年度": "2025",
      "EPS预测": {
        "T年": "0.47",
        "T+1年": "0.67",
        "T+2年": "0.90"
      },
      "标题": "吉祥航空(603885)发动机影响犹在，盈利高弹性不改",
      "研究机构": "中泰证券"
    },
    {
      "序号": 110,
      "报告日期": "2025-11-01",
      "证券代码": "002027",
      "证券简称": "分众传媒",
      "评级": "买入",
      "评级变化": "维持",
      "目标价": "--",
      "EPS实际值(元)": "0.357(2024)",
      "T年度": "2025",
      "EPS预测": {
        "T年": "0.39",
        "T+1年": "0.47",
        "T+2年": "0.53"
      },
      "标题": "分众传媒(002027)毛利率创阶段新高，持续重视股东回报",
      "研究机构": "长江证券"
    },
    {
      "序号": 111,
      "报告日期": "2025-11-01",
      "证券代码": "603983",
      "证券简称": "丸美生物",
      "评级": "增持",
      "评级变化": "维持",
      "目标价": "44.21",
      "EPS实际值(元)": "0.85(2024)",
      "T年度": "2025",
      "EPS预测": {
        "T年": "0.92",
        "T+1年": "1.17",
        "T+2年": "1.40"
      },
      "标题": "丸美生物(603983)Q3毛利率继续优化",
      "研究机构": "华泰证券"
    },
    {
      "序号": 112,
      "报告日期": "2025-11-01",
      "证券代码": "600809",
      "证券简称": "山西汾酒",
      "评级": "买入",
      "评级变化": "维持",
      "目标价": "--",
      "EPS实际值(元)": "10.0354(2024)",
      "T年度": "2025",
      "EPS预测": {
        "T年": "10.16",
        "T+1年": "10.77",
        "T+2年": "11.54"
      },
      "标题": "山西汾酒(600809)2025年三季报点评：延续平稳增长，省外继续扩张",
      "研究机构": "光大证券"
    },
    {
      "序号": 113,
      "报告日期": "2025-11-01",
      "证券代码": "605300",
      "证券简称": "佳禾食品",
      "评级": "中性",
      "评级变化": "维持",
      "目标价": "11.10",
      "EPS实际值(元)": "0.21(2024)",
      "T年度": "2025",
      "EPS预测": {
        "T年": "0.10",
        "T+1年": "0.37",
        "T+2年": "0.50"
      },
      "标题": "佳禾食品(605300)三季报点评：产品结构调整，咖啡成长延续",
      "研究机构": "国泰海通"
    },
    {
      "序号": 114,
      "报告日期": "2025-11-01",
      "证券代码": "600809",
      "证券简称": "山西汾酒",
      "评级": "买入",
      "评级变化": "维持",
      "目标价": "--",
      "EPS实际值(元)": "10.0354(2024)",
      "T年度": "2025",
      "EPS预测": {
        "T年": "10.07",
        "T+1年": "10.98",
        "T+2年": "12.10"
      },
      "标题": "山西汾酒(600809)Q3稳健增长，省外逆势突破",
      "研究机构": "财通证券"
    },
    {
      "序号": 115,
      "报告日期": "2025-11-01",
      "证券代码": "002555",
      "证券简称": "三七互娱",
      "评级": "买入",
      "评级变化": "维持",
      "目标价": "--",
      "EPS实际值(元)": "1.21(2024)",
      "T年度": "2025",
      "EPS预测": {
        "T年": "1.40",
        "T+1年": "1.53",
        "T+2年": "1.65"
      },
      "标题": "三七互娱(002555)业绩超预期，持续优化投放和股东回报",
      "研究机构": "长江证券"
    },
    {
      "序号": 116,
      "报告日期": "2025-11-01",
      "证券代码": "688008",
      "证券简称": "澜起科技",
      "评级": "买入",
      "评级变化": "维持",
      "目标价": "178.80",
      "EPS实际值(元)": "1.25(2024)",
      "T年度": "2025",
      "EPS预测": {
        "T年": "1.91",
        "T+1年": "2.75",
        "T+2年": "3.78"
      },
      "标题": "澜起科技(688008)MRDIMM产业化落地有望加速",
      "研究机构": "华泰证券"
    },
    {
      "序号": 117,
      "报告日期": "2025-11-01",
      "证券代码": "002600",
      "证券简称": "领益智造",
      "评级": "买入",
      "评级变化": "维持",
      "目标价": "--",
      "EPS实际值(元)": "0.25(2024)",
      "T年度": "2025",
      "EPS预测": {
        "T年": "0.36",
        "T+1年": "0.48",
        "T+2年": "0.65"
      },
      "标题": "领益智造(002600)Q3业绩持续增长，新业务持续突破",
      "研究机构": "国金证券"
    },
    {
      "序号": 118,
      "报告日期": "2025-11-01",
      "证券代码": "688608",
      "证券简称": "恒玄科技",
      "评级": "增持",
      "评级变化": "维持",
      "目标价": "294.20",
      "EPS实际值(元)": "3.8585(2024)",
      "T年度": "2025",
      "EPS预测": {
        "T年": "4.03",
        "T+1年": "5.32",
        "T+2年": "7.98"
      },
      "标题": "恒玄科技(688608)国补效应递减，静候6000系列落地",
      "研究机构": "华泰证券"
    },
    {
      "序号": 119,
      "报告日期": "2025-11-01",
      "证券代码": "600905",
      "证券简称": "三峡能源",
      "评级": "买入",
      "评级变化": "维持",
      "目标价": "4.75",
      "EPS实际值(元)": "0.2135(2024)",
      "T年度": "2025",
      "EPS预测": {
        "T年": "0.19",
        "T+1年": "0.25",
        "T+2年": "0.28"
      },
      "标题": "三峡能源(600905)短期业绩压力不改长期增长基础",
      "研究机构": "华泰证券"
    },
    {
      "序号": 120,
      "报告日期": "2025-11-01",
      "证券代码": "688696",
      "证券简称": "极米科技",
      "评级": "增持",
      "评级变化": "维持",
      "目标价": "--",
      "EPS实际值(元)": "1.75(2024)",
      "T年度": "2025",
      "EPS预测": {
        "T年": "2.75",
        "T+1年": "3.29",
        "T+2年": "3.72"
      },
      "标题": "极米科技(688696)Q3亏损同比收窄，DLP龙头地位稳固",
      "研究机构": "国盛证券"
    },
    {
      "序号": 121,
      "报告日期": "2025-11-01",
      "证券代码": "600919",
      "证券简称": "江苏银行",
      "评级": "买入",
      "评级变化": "维持",
      "目标价": "--",
      "EPS实际值(元)": "1.65(2024)",
      "T年度": "2025",
      "EPS预测": {
        "T年": "1.88",
        "T+1年": "1.98",
        "T+2年": "2.07"
      },
      "标题": "江苏银行(600919)2025年三季报点评：业绩增速韧性较强，资本安全边际增厚",
      "研究机构": "光大证券"
    },
    {
      "序号": 122,
      "报告日期": "2025-11-01",
      "证券代码": "600919",
      "证券简称": "江苏银行",
      "评级": "买入",
      "评级变化": "维持",
      "目标价": "--",
      "EPS实际值(元)": "1.65(2024)",
      "T年度": "2025",
      "EPS预测": {
        "T年": "1.91",
        "T+1年": "2.03",
        "T+2年": "2.15"
      },
      "标题": "江苏银行(600919)详解江苏银行2025年三季报：业绩韧性强；存贷高增；资产质量稳健",
      "研究机构": "中泰证券"
    },
    {
      "序号": 123,
      "报告日期": "2025-11-01",
      "证券代码": "300677",
      "证券简称": "英科医疗",
      "评级": "买入",
      "评级变化": "维持",
      "目标价": "--",
      "EPS实际值(元)": "2.26(2024)",
      "T年度": "2025",
      "EPS预测": {
        "T年": "2.18",
        "T+1年": "2.81",
        "T+2年": "3.56"
      },
      "标题": "英科医疗(300677)手套价格回暖，海外扩产增加新动能",
      "研究机构": "太平洋证券"
    },
    {
      "序号": 124,
      "报告日期": "2025-11-01",
      "证券代码": "301039",
      "证券简称": "中集车辆",
      "评级": "增持",
      "评级变化": "维持",
      "目标价": "--",
      "EPS实际值(元)": "0.56(2024)",
      "T年度": "2025",
      "EPS预测": {
        "T年": "0.50",
        "T+1年": "0.67",
        "T+2年": "1.02"
      },
      "标题": "中集车辆(301039)公司动态研究：2025Q3北美市场弱景气持续，前三季度中国／全球南方市场收入与盈利能力同比皆提升显著",
      "研究机构": "国海证券"
    },
    {
      "序号": 125,
      "报告日期": "2025-11-01",
      "证券代码": "600030",
      "证券简称": "中信证券",
      "评级": "买入",
      "评级变化": "维持",
      "目标价": "--",
      "EPS实际值(元)": "1.41(2024)",
      "T年度": "2025",
      "EPS预测": {
        "T年": "1.93",
        "T+1年": "2.12",
        "T+2年": "2.34"
      },
      "标题": "中信证券(600030)25Q3点评：净利润增38%25，经纪与投资双轮驱动",
      "研究机构": "中泰证券"
    },
    {
      "序号": 126,
      "报告日期": "2025-11-01",
      "证券代码": "601111",
      "证券简称": "中国国航",
      "评级": "增持",
      "评级变化": "维持",
      "目标价": "--",
      "EPS实际值(元)": "-0.01(2024)",
      "T年度": "2025",
      "EPS预测": {
        "T年": "0.05",
        "T+1年": "0.31",
        "T+2年": "0.58"
      },
      "标题": "中国国航(601111)2025年第三季度报告点评：Q3盈利下滑11%25，控股股东及关联方拟全额认购定增",
      "研究机构": "西部证券"
    },
    {
      "序号": 127,
      "报告日期": "2025-11-01",
      "证券代码": "600522",
      "证券简称": "中天科技",
      "评级": "买入",
      "评级变化": "维持",
      "目标价": "--",
      "EPS实际值(元)": "0.835(2024)",
      "T年度": "2025",
      "EPS预测": {
        "T年": "0.90",
        "T+1年": "1.02",
        "T+2年": "1.12"
      },
      "标题": "中天科技(600522)经营现金流显著改善，空芯光纤商用突破",
      "研究机构": "长江证券"
    },
    {
      "序号": 128,
      "报告日期": "2025-11-01",
      "证券代码": "601118",
      "证券简称": "海南橡胶",
      "评级": "增持",
      "评级变化": "维持",
      "目标价": "--",
      "EPS实际值(元)": "0.0242(2024)",
      "T年度": "2025",
      "EPS预测": {
        "T年": "0.02",
        "T+1年": "0.06",
        "T+2年": "0.11"
      },
      "标题": "海南橡胶(601118)2025三季报点评：期间费用减少，地租收入增加，Q3业绩维持同比减亏趋势",
      "研究机构": "国信证券"
    },
    {
      "序号": 129,
      "报告日期": "2025-11-01",
      "证券代码": "688037",
      "证券简称": "芯源微",
      "评级": "增持",
      "评级变化": "维持",
      "目标价": "--",
      "EPS实际值(元)": "1.01(2024)",
      "T年度": "2025",
      "EPS预测": {
        "T年": "1.00",
        "T+1年": "2.25",
        "T+2年": "3.55"
      },
      "标题": "芯源微(688037)25Q3业绩承压，Track+湿法+先进封装成长逻辑出色",
      "研究机构": "华西证券"
    },
    {
      "序号": 130,
      "报告日期": "2025-11-01",
      "证券代码": "000938",
      "证券简称": "紫光股份",
      "评级": "买入",
      "评级变化": "维持",
      "目标价": "--",
      "EPS实际值(元)": "0.5498(2024)",
      "T年度": "2025",
      "EPS预测": {
        "T年": "0.63",
        "T+1年": "0.80",
        "T+2年": "1.04"
      },
      "标题": "紫光股份(000938)AI拉动营收增长，毛利率影响盈利空间承压",
      "研究机构": "华西证券"
    },
    {
      "序号": 131,
      "报告日期": "2025-11-01",
      "证券代码": "601126",
      "证券简称": "四方股份",
      "评级": "买入",
      "评级变化": "维持",
      "目标价": "--",
      "EPS实际值(元)": "0.87(2024)",
      "T年度": "2025",
      "EPS预测": {
        "T年": "0.99",
        "T+1年": "1.19",
        "T+2年": "1.45"
      },
      "标题": "四方股份(601126)2025年三季报点评：业绩稳步增长，SST等产品逐步发力",
      "研究机构": "国联民生"
    },
    {
      "序号": 132,
      "报告日期": "2025-11-01",
      "证券代码": "688100",
      "证券简称": "威胜信息",
      "评级": "增持",
      "评级变化": "维持",
      "目标价": "--",
      "EPS实际值(元)": "1.28(2024)",
      "T年度": "2025",
      "EPS预测": {
        "T年": "1.48",
        "T+1年": "1.77",
        "T+2年": "2.12"
      },
      "标题": "威胜信息(688100)业绩稳健增长，国际化布局再上一楼",
      "研究机构": "华西证券"
    },
    {
      "序号": 133,
      "报告日期": "2025-11-01",
      "证券代码": "601128",
      "证券简称": "常熟银行",
      "评级": "买入",
      "评级变化": "维持",
      "目标价": "--",
      "EPS实际值(元)": "1.26(2024)",
      "T年度": "2025",
      "EPS预测": {
        "T年": "1.32",
        "T+1年": "1.46",
        "T+2年": "1.56"
      },
      "标题": "常熟银行(601128)2025年三季报点评：净息差、净利差环比基本持平，个人经营贷增长平稳",
      "研究机构": "国海证券"
    },
    {
      "序号": 134,
      "报告日期": "2025-11-01",
      "证券代码": "601208",
      "证券简称": "东材科技",
      "评级": "买入",
      "评级变化": "维持",
      "目标价": "--",
      "EPS实际值(元)": "0.2(2024)",
      "T年度": "2025",
      "EPS预测": {
        "T年": "0.39",
        "T+1年": "0.76",
        "T+2年": "1.41"
      },
      "标题": "东材科技(601208)2025年Q3业绩点评：毛利实现持续高增，电子材料&光学膜同环比亮眼",
      "研究机构": "中泰证券"
    },
    {
      "序号": 135,
      "报告日期": "2025-11-01",
      "证券代码": "601665",
      "证券简称": "齐鲁银行",
      "评级": "增持",
      "评级变化": "维持",
      "目标价": "--",
      "EPS实际值(元)": "0.97(2024)",
      "T年度": "2025",
      "EPS预测": {
        "T年": "1.16",
        "T+1年": "1.28",
        "T+2年": "1.39"
      },
      "标题": "齐鲁银行(601665)详解齐鲁银行2025年三季报：利润维持高增；扩表稳健；拨备安全垫持续增厚",
      "研究机构": "中泰证券"
    },
    {
      "序号": 136,
      "报告日期": "2025-11-01",
      "证券代码": "601668",
      "证券简称": "中国建筑",
      "评级": "买入",
      "评级变化": "维持",
      "目标价": "9.50",
      "EPS实际值(元)": "1.11(2024)",
      "T年度": "2025",
      "EPS预测": {
        "T年": "1.13",
        "T+1年": "1.14",
        "T+2年": "1.16"
      },
      "标题": "中国建筑(601668)建筑新签、地产销售均保持稳健",
      "研究机构": "华泰证券"
    },
    {
      "序号": 137,
      "报告日期": "2025-11-01",
      "证券代码": "002120",
      "证券简称": "韵达股份",
      "评级": "增持",
      "评级变化": "维持",
      "目标价": "8.79",
      "EPS实际值(元)": "0.66(2024)",
      "T年度": "2025",
      "EPS预测": {
        "T年": "--",
        "T+1年": "--",
        "T+2年": "--"
      },
      "标题": "韵达股份(002120)3Q25单票扣非净利润环比提升，修复仍在途中",
      "研究机构": "中金公司"
    },
    {
      "序号": 138,
      "报告日期": "2025-11-01",
      "证券代码": "002345",
      "证券简称": "潮宏基",
      "评级": "增持",
      "评级变化": "维持",
      "目标价": "16.39",
      "EPS实际值(元)": "0.22(2024)",
      "T年度": "2025",
      "EPS预测": {
        "T年": "0.53",
        "T+1年": "0.66",
        "T+2年": "--"
      },
      "标题": "潮宏基(002345)剔除女包业务减值后，收入利润均有高增",
      "研究机构": "中金公司"
    },
    {
      "序号": 139,
      "报告日期": "2025-11-01",
      "证券代码": "601825",
      "证券简称": "沪农商行",
      "评级": "增持",
      "评级变化": "维持",
      "目标价": "--",
      "EPS实际值(元)": "1.27(2024)",
      "T年度": "2025",
      "EPS预测": {
        "T年": "1.29",
        "T+1年": "1.31",
        "T+2年": "1.35"
      },
      "标题": "沪农商行(601825)详解沪农商行2025年三季报业绩向好，存贷稳增，拨备回升",
      "研究机构": "中泰证券"
    },
    {
      "序号": 140,
      "报告日期": "2025-11-01",
      "证券代码": "601877",
      "证券简称": "正泰电器",
      "评级": "买入",
      "评级变化": "维持",
      "目标价": "--",
      "EPS实际值(元)": "1.81(2024)",
      "T年度": "2025",
      "EPS预测": {
        "T年": "2.30",
        "T+1年": "2.68",
        "T+2年": "3.09"
      },
      "标题": "正泰电器(601877)2025年三季报点评：盈利能力持续改善，积极布局数据中心领域",
      "研究机构": "国联民生"
    },
    {
      "序号": 141,
      "报告日期": "2025-11-01",
      "证券代码": "601919",
      "证券简称": "中远海控",
      "评级": "买入",
      "评级变化": "维持",
      "目标价": "17.70",
      "EPS实际值(元)": "3.08(2024)",
      "T年度": "2025",
      "EPS预测": {
        "T年": "2.02",
        "T+1年": "1.01",
        "T+2年": "1.53"
      },
      "标题": "中远海控(601919)不确定性扰动集运市场前景",
      "研究机构": "华泰证券"
    },
    {
      "序号": 142,
      "报告日期": "2025-11-01",
      "证券代码": "603444",
      "证券简称": "吉比特",
      "评级": "买入",
      "评级变化": "维持",
      "目标价": "--",
      "EPS实际值(元)": "13.15(2024)",
      "T年度": "2025",
      "EPS预测": {
        "T年": "23.48",
        "T+1年": "26.41",
        "T+2年": "28.96"
      },
      "标题": "吉比特(603444)业绩位于预告区间上限，出海及小游戏贡献显著增量",
      "研究机构": "长江证券"
    },
    {
      "序号": 143,
      "报告日期": "2025-11-01",
      "证券代码": "002444",
      "证券简称": "巨星科技",
      "评级": "增持",
      "评级变化": "维持",
      "目标价": "38.22",
      "EPS实际值(元)": "1.9286(2024)",
      "T年度": "2025",
      "EPS预测": {
        "T年": "2.14",
        "T+1年": "2.58",
        "T+2年": "--"
      },
      "标题": "巨星科技(002444)公司毛利率持续提升，看好行业需求复苏",
      "研究机构": "中金公司"
    },
    {
      "序号": 144,
      "报告日期": "2025-11-01",
      "证券代码": "603501",
      "证券简称": "豪威集团",
      "评级": "买入",
      "评级变化": "维持",
      "目标价": "--",
      "EPS实际值(元)": "2.77(2024)",
      "T年度": "2025",
      "EPS预测": {
        "T年": "3.56",
        "T+1年": "4.70",
        "T+2年": "5.79"
      },
      "标题": "豪威集团(603501)车载业务强势驱动，看好新品布局下长期增长",
      "研究机构": "长江证券"
    },
    {
      "序号": 145,
      "报告日期": "2025-11-01",
      "证券代码": "688266",
      "证券简称": "泽璟制药",
      "评级": "买入",
      "评级变化": "维持",
      "目标价": "--",
      "EPS实际值(元)": "-0.52(2024)",
      "T年度": "2025",
      "EPS预测": {
        "T年": "0.41",
        "T+1年": "0.72",
        "T+2年": "2.12"
      },
      "标题": "泽璟制药-U(688266)吉卡昔替尼扩大自免适应症，多抗研究再登ESMO",
      "研究机构": "华安证券"
    },
    {
      "序号": 146,
      "报告日期": "2025-11-01",
      "证券代码": "601991",
      "证券简称": "大唐发电",
      "评级": "买入",
      "评级变化": "维持",
      "目标价": "--",
      "EPS实际值(元)": "0.1629(2024)",
      "T年度": "2025",
      "EPS预测": {
        "T年": "0.35",
        "T+1年": "0.41",
        "T+2年": "0.47"
      },
      "标题": "大唐发电(601991)公司点评报告：季度电量同比微增，燃料成本优化彰显盈利弹性",
      "研究机构": "方正证券"
    },
    {
      "序号": 147,
      "报告日期": "2025-11-01",
      "证券代码": "603538",
      "证券简称": "美诺华",
      "评级": "增持",
      "评级变化": "维持",
      "目标价": "--",
      "EPS实际值(元)": "0.31(2024)",
      "T年度": "2025",
      "EPS预测": {
        "T年": "0.62",
        "T+1年": "0.84",
        "T+2年": "1.06"
      },
      "标题": "美诺华(603538)制剂业务持续发力，递送系统有多方向拓展潜力",
      "研究机构": "天风证券"
    },
    {
      "序号": 148,
      "报告日期": "2025-11-01",
      "证券代码": "603986",
      "证券简称": "兆易创新",
      "评级": "买入",
      "评级变化": "维持",
      "目标价": "--",
      "EPS实际值(元)": "1.66(2024)",
      "T年度": "2025",
      "EPS预测": {
        "T年": "2.39",
        "T+1年": "3.55",
        "T+2年": "4.35"
      },
      "标题": "兆易创新(603986)三季度业绩如期兑现",
      "研究机构": "长江证券"
    },
    {
      "序号": 149,
      "报告日期": "2025-11-01",
      "证券代码": "603317",
      "证券简称": "天味食品",
      "评级": "买入",
      "评级变化": "维持",
      "目标价": "--",
      "EPS实际值(元)": "0.5926(2024)",
      "T年度": "2025",
      "EPS预测": {
        "T年": "0.56",
        "T+1年": "0.61",
        "T+2年": "0.66"
      },
      "标题": "天味食品(603317)Q3收入快速增长，外延发展再下一城",
      "研究机构": "中泰证券"
    },
    {
      "序号": 150,
      "报告日期": "2025-11-01",
      "证券代码": "688185",
      "证券简称": "康希诺",
      "评级": "未知",
      "评级变化": "未知",
      "目标价": "--",
      "EPS实际值(元)": "-1.53(2024)",
      "T年度": "2025",
      "EPS预测": {
        "T年": "0.06",
        "T+1年": "0.18",
        "T+2年": "0.45"
      },
      "标题": "康希诺(688185)2025年三季报点评：利润同比扭亏，创新管线持续放量",
      "研究机构": "西南证券"
    },
    {
      "序号": 151,
      "报告日期": "2025-11-01",
      "证券代码": "605376",
      "证券简称": "博迁新材",
      "评级": "买入",
      "评级变化": "维持",
      "目标价": "--",
      "EPS实际值(元)": "0.33(2024)",
      "T年度": "2025",
      "EPS预测": {
        "T年": "0.84",
        "T+1年": "1.56",
        "T+2年": "1.90"
      },
      "标题": "博迁新材(605376)Q3短期成本抬升影响盈利，资本开支和大订单互相印证镍粉高景气度",
      "研究机构": "天风证券"
    },
    {
      "序号": 152,
      "报告日期": "2025-11-01",
      "证券代码": "920002",
      "证券简称": "万达轴承",
      "评级": "增持",
      "评级变化": "维持",
      "目标价": "--",
      "EPS实际值(元)": "1.92(2024)",
      "T年度": "2025",
      "EPS预测": {
        "T年": "1.29",
        "T+1年": "1.45",
        "T+2年": "1.62"
      },
      "标题": "万达轴承(920002)北交所信息更新：叉车门架轴承产品工艺高壁垒，拓展工业+人形机器人新领域",
      "研究机构": "开源证券"
    },
    {
      "序号": 153,
      "报告日期": "2025-11-01",
      "证券代码": "002851",
      "证券简称": "麦格米特",
      "评级": "增持",
      "评级变化": "维持",
      "目标价": "95.00",
      "EPS实际值(元)": "0.8651(2024)",
      "T年度": "2025",
      "EPS预测": {
        "T年": "--",
        "T+1年": "--",
        "T+2年": "--"
      },
      "标题": "麦格米特(002851)3Q25低于市场预期，海外需求有所波动",
      "研究机构": "中金公司"
    },
    {
      "序号": 154,
      "报告日期": "2025-11-01",
      "证券代码": "603833",
      "证券简称": "欧派家居",
      "评级": "买入",
      "评级变化": "维持",
      "目标价": "--",
      "EPS实际值(元)": "4.29(2024)",
      "T年度": "2025",
      "EPS预测": {
        "T年": "4.01",
        "T+1年": "4.38",
        "T+2年": "4.77"
      },
      "标题": "欧派家居(603833)Q3利润率基数扰动，大家居改革深化",
      "研究机构": "华福证券"
    },
    {
      "序号": 155,
      "报告日期": "2025-11-01",
      "证券代码": "002019",
      "证券简称": "亿帆医药",
      "评级": "买入",
      "评级变化": "维持",
      "目标价": "--",
      "EPS实际值(元)": "0.32(2024)",
      "T年度": "2025",
      "EPS预测": {
        "T年": "0.49",
        "T+1年": "0.58",
        "T+2年": "0.69"
      },
      "标题": "亿帆医药(002019)亿立舒销售继续高速增长，IL-15双融合蛋白IND",
      "研究机构": "华安证券"
    },
    {
      "序号": 156,
      "报告日期": "2025-11-01",
      "证券代码": "920541",
      "证券简称": "铁大科技",
      "评级": "增持",
      "评级变化": "维持",
      "目标价": "--",
      "EPS实际值(元)": "0.42(2024)",
      "T年度": "2025",
      "EPS预测": {
        "T年": "0.54",
        "T+1年": "0.61",
        "T+2年": "0.68"
      },
      "标题": "铁大科技(920541)北交所信息更新：持股狗熊机器人已完成变更、通过CMMI5，2025Q1-3归母净利润+37%",
      "研究机构": "开源证券"
    },
    {
      "序号": 157,
      "报告日期": "2025-11-01",
      "证券代码": "603885",
      "证券简称": "吉祥航空",
      "评级": "增持",
      "评级变化": "维持",
      "目标价": "--",
      "EPS实际值(元)": "0.42(2024)",
      "T年度": "2025",
      "EPS预测": {
        "T年": "0.46",
        "T+1年": "0.82",
        "T+2年": "1.00"
      },
      "标题": "吉祥航空(603885)2025年第三季度报告点评：发动机维修拖累盈利增长，回购彰显公司信心",
      "研究机构": "西部证券"
    },
    {
      "序号": 158,
      "报告日期": "2025-11-01",
      "证券代码": "603918",
      "证券简称": "金桥信息",
      "评级": "买入",
      "评级变化": "维持",
      "目标价": "--",
      "EPS实际值(元)": "-0.17(2024)",
      "T年度": "2025",
      "EPS预测": {
        "T年": "0.11",
        "T+1年": "0.29",
        "T+2年": "0.52"
      },
      "标题": "金桥信息(603918)2025年三季报点评：Q3业绩短期承压，AI+司法产品有望加速迭代",
      "研究机构": "国联民生"
    },
    {
      "序号": 159,
      "报告日期": "2025-11-01",
      "证券代码": "605338",
      "证券简称": "巴比食品",
      "评级": "买入",
      "评级变化": "维持",
      "目标价": "--",
      "EPS实际值(元)": "1.12(2024)",
      "T年度": "2025",
      "EPS预测": {
        "T年": "1.21",
        "T+1年": "1.36",
        "T+2年": "1.49"
      },
      "标题": "巴比食品(605338)2025年三季报点评：直营门店扩张提速，双轮驱动渐入佳境",
      "研究机构": "西部证券"
    },
    {
      "序号": 160,
      "报告日期": "2025-11-01",
      "证券代码": "688526",
      "证券简称": "科前生物",
      "评级": "买入",
      "评级变化": "维持",
      "目标价": "--",
      "EPS实际值(元)": "0.82(2024)",
      "T年度": "2025",
      "EPS预测": {
        "T年": "0.93",
        "T+1年": "1.12",
        "T+2年": "1.31"
      },
      "标题": "科前生物(688526)2025年三季报点评：经营业绩持续向好，产品矩阵不断完善",
      "研究机构": "国海证券"
    },
    {
      "序号": 161,
      "报告日期": "2025-11-01",
      "证券代码": "002078",
      "证券简称": "太阳纸业",
      "评级": "买入",
      "评级变化": "维持",
      "目标价": "--",
      "EPS实际值(元)": "1.11(2024)",
      "T年度": "2025",
      "EPS预测": {
        "T年": "1.23",
        "T+1年": "1.43",
        "T+2年": "1.67"
      },
      "标题": "太阳纸业(002078)25Q4改善可期",
      "研究机构": "天风证券"
    },
    {
      "序号": 162,
      "报告日期": "2025-11-01",
      "证券代码": "688526",
      "证券简称": "科前生物",
      "评级": "买入",
      "评级变化": "维持",
      "目标价": "--",
      "EPS实际值(元)": "0.82(2024)",
      "T年度": "2025",
      "EPS预测": {
        "T年": "1.00",
        "T+1年": "1.16",
        "T+2年": "1.35"
      },
      "标题": "科前生物(688526)25年三季报点评：前三季度经营业绩同比回暖，研发能力持续强化",
      "研究机构": "西部证券"
    },
    {
      "序号": 163,
      "报告日期": "2025-11-01",
      "证券代码": "002734",
      "证券简称": "利民股份",
      "评级": "买入",
      "评级变化": "维持",
      "目标价": "--",
      "EPS实际值(元)": "0.23(2024)",
      "T年度": "2025",
      "EPS预测": {
        "T年": "1.14",
        "T+1年": "1.31",
        "T+2年": "1.45"
      },
      "标题": "利民股份(002734)2025年三季报点评：核心产品景气回升，Q3业绩同比大幅改善",
      "研究机构": "国海证券"
    },
    {
      "序号": 164,
      "报告日期": "2025-11-01",
      "证券代码": "002714",
      "证券简称": "牧原股份",
      "评级": "买入",
      "评级变化": "维持",
      "目标价": "--",
      "EPS实际值(元)": "3.3(2024)",
      "T年度": "2025",
      "EPS预测": {
        "T年": "3.08",
        "T+1年": "4.28",
        "T+2年": "6.01"
      },
      "标题": "牧原股份(002714)出栏、成本目标达成可期，Q3屠宰肉食业务盈利",
      "研究机构": "华安证券"
    },
    {
      "序号": 165,
      "报告日期": "2025-11-01",
      "证券代码": "002831",
      "证券简称": "裕同科技",
      "评级": "买入",
      "评级变化": "维持",
      "目标价": "--",
      "EPS实际值(元)": "1.54(2024)",
      "T年度": "2025",
      "EPS预测": {
        "T年": "1.74",
        "T+1年": "2.00",
        "T+2年": "2.30"
      },
      "标题": "裕同科技(002831)25Q3盈利能力稳步提升",
      "研究机构": "天风证券"
    },
    {
      "序号": 166,
      "报告日期": "2025-11-01",
      "证券代码": "002245",
      "证券简称": "蔚蓝锂芯",
      "评级": "增持",
      "评级变化": "维持",
      "目标价": "--",
      "EPS实际值(元)": "0.4235(2024)",
      "T年度": "2025",
      "EPS预测": {
        "T年": "0.66",
        "T+1年": "0.82",
        "T+2年": "1.01"
      },
      "标题": "蔚蓝锂芯(002245)公司跟踪报告：锂电池板块持续向好，LED出口阶段性扰动",
      "研究机构": "方正证券"
    },
    {
      "序号": 167,
      "报告日期": "2025-11-01",
      "证券代码": "300601",
      "证券简称": "康泰生物",
      "评级": "增持",
      "评级变化": "维持",
      "目标价": "18.96",
      "EPS实际值(元)": "0.18(2024)",
      "T年度": "2025",
      "EPS预测": {
        "T年": "0.06",
        "T+1年": "0.34",
        "T+2年": "0.46"
      },
      "标题": "康泰生物(300601)业绩短期承压，研发与出海取得多项积极进展",
      "研究机构": "国投证券"
    },
    {
      "序号": 168,
      "报告日期": "2025-11-01",
      "证券代码": "600132",
      "证券简称": "重庆啤酒",
      "评级": "增持",
      "评级变化": "维持",
      "目标价": "63.70",
      "EPS实际值(元)": "2.3(2024)",
      "T年度": "2025",
      "EPS预测": {
        "T年": "--",
        "T+1年": "--",
        "T+2年": "--"
      },
      "标题": "重庆啤酒(600132)3Q25产品结构升级持续，费用投放边际加大",
      "研究机构": "中金公司"
    },
    {
      "序号": 169,
      "报告日期": "2025-11-01",
      "证券代码": "301376",
      "证券简称": "致欧科技",
      "评级": "买入",
      "评级变化": "维持",
      "目标价": "--",
      "EPS实际值(元)": "0.83(2024)",
      "T年度": "2025",
      "EPS预测": {
        "T年": "0.94",
        "T+1年": "1.24",
        "T+2年": "1.56"
      },
      "标题": "致欧科技(301376)强化产业链调整，盈利改善可期",
      "研究机构": "天风证券"
    },
    {
      "序号": 170,
      "报告日期": "2025-11-01",
      "证券代码": "600486",
      "证券简称": "扬农化工",
      "评级": "买入",
      "评级变化": "维持",
      "目标价": "--",
      "EPS实际值(元)": "2.978(2024)",
      "T年度": "2025",
      "EPS预测": {
        "T年": "3.21",
        "T+1年": "4.00",
        "T+2年": "4.77"
      },
      "标题": "扬农化工(600486)三季度销售增势良好，业绩持稳",
      "研究机构": "天风证券"
    },
    {
      "序号": 171,
      "报告日期": "2025-11-01",
      "证券代码": "600597",
      "证券简称": "光明乳业",
      "评级": "增持",
      "评级变化": "维持",
      "目标价": "9.50",
      "EPS实际值(元)": "0.52(2024)",
      "T年度": "2025",
      "EPS预测": {
        "T年": "--",
        "T+1年": "--",
        "T+2年": "--"
      },
      "标题": "光明乳业(600597)关注需求复苏情况及新莱特北岛资产处置进展",
      "研究机构": "中金公司"
    },
    {
      "序号": 172,
      "报告日期": "2025-11-01",
      "证券代码": "601818",
      "证券简称": "光大银行",
      "评级": "增持",
      "评级变化": "维持",
      "目标价": "--",
      "EPS实际值(元)": "0.62(2024)",
      "T年度": "2025",
      "EPS预测": {
        "T年": "0.71",
        "T+1年": "0.71",
        "T+2年": "0.72"
      },
      "标题": "光大银行(601818)2025年三季报点评：营收结构有亮点，财富管理质效提升",
      "研究机构": "开源证券"
    },
    {
      "序号": 173,
      "报告日期": "2025-11-01",
      "证券代码": "600885",
      "证券简称": "宏发股份",
      "评级": "增持",
      "评级变化": "维持",
      "目标价": "35.00",
      "EPS实际值(元)": "1.56(2024)",
      "T年度": "2025",
      "EPS预测": {
        "T年": "--",
        "T+1年": "--",
        "T+2年": "--"
      },
      "标题": "宏发股份(600885)3Q25业绩符合预期，看好AIDC业务发展机遇",
      "研究机构": "中金公司"
    },
    {
      "序号": 174,
      "报告日期": "2025-11-01",
      "证券代码": "600809",
      "证券简称": "山西汾酒",
      "评级": "增持",
      "评级变化": "维持",
      "目标价": "--",
      "EPS实际值(元)": "10.0354(2024)",
      "T年度": "2025",
      "EPS预测": {
        "T年": "10.03",
        "T+1年": "10.76",
        "T+2年": "11.66"
      },
      "标题": "山西汾酒(600809)业绩稳健增长，省外表现亮眼",
      "研究机构": "太平洋证券"
    },
    {
      "序号": 175,
      "报告日期": "2025-11-01",
      "证券代码": "601127",
      "证券简称": "赛力斯",
      "评级": "买入",
      "评级变化": "维持",
      "目标价": "--",
      "EPS实际值(元)": "3.94(2024)",
      "T年度": "2025",
      "EPS预测": {
        "T年": "5.55",
        "T+1年": "7.82",
        "T+2年": "9.67"
      },
      "标题": "赛力斯(601127)港股上市推动全球品牌，人形机器人加速落地",
      "研究机构": "太平洋证券"
    },
    {
      "序号": 176,
      "报告日期": "2025-11-01",
      "证券代码": "301327",
      "证券简称": "华宝新能",
      "评级": "买入",
      "评级变化": "维持",
      "目标价": "--",
      "EPS实际值(元)": "1.93(2024)",
      "T年度": "2025",
      "EPS预测": {
        "T年": "1.16",
        "T+1年": "3.01",
        "T+2年": "4.43"
      },
      "标题": "华宝新能(301327)2025三季报业绩点评：美国关税冲击Q3利润短期下滑，家庭应急绿电收入放量",
      "研究机构": "西部证券"
    },
    {
      "序号": 177,
      "报告日期": "2025-11-01",
      "证券代码": "603489",
      "证券简称": "八方股份",
      "评级": "增持",
      "评级变化": "维持",
      "目标价": "35.00",
      "EPS实际值(元)": "0.27(2024)",
      "T年度": "2025",
      "EPS预测": {
        "T年": "--",
        "T+1年": "--",
        "T+2年": "--"
      },
      "标题": "八方股份(603489)3Q迎来业绩拐点，电踏车进入新一轮成长周期",
      "研究机构": "中金公司"
    },
    {
      "序号": 178,
      "报告日期": "2025-11-01",
      "证券代码": "601628",
      "证券简称": "中国人寿",
      "评级": "买入",
      "评级变化": "维持",
      "目标价": "--",
      "EPS实际值(元)": "3.78(2024)",
      "T年度": "2025",
      "EPS预测": {
        "T年": "--",
        "T+1年": "--",
        "T+2年": "--"
      },
      "标题": "中国人寿(601628)2025年三季报点评：NBV增速环比提升，Q3单季净利润同比高增",
      "研究机构": "国联民生"
    },
    {
      "序号": 179,
      "报告日期": "2025-11-01",
      "证券代码": "603198",
      "证券简称": "迎驾贡酒",
      "评级": "增持",
      "评级变化": "维持",
      "目标价": "--",
      "EPS实际值(元)": "3.24(2024)",
      "T年度": "2025",
      "EPS预测": {
        "T年": "2.52",
        "T+1年": "2.72",
        "T+2年": "3.02"
      },
      "标题": "迎驾贡酒(603198)行业调整期业绩承压，持续出清静待复苏",
      "研究机构": "太平洋证券"
    },
    {
      "序号": 180,
      "报告日期": "2025-11-01",
      "证券代码": "000425",
      "证券简称": "徐工机械",
      "评级": "增持",
      "评级变化": "维持",
      "目标价": "--",
      "EPS实际值(元)": "0.51(2024)",
      "T年度": "2025",
      "EPS预测": {
        "T年": "0.64",
        "T+1年": "0.81",
        "T+2年": "0.99"
      },
      "标题": "徐工机械(000425)2025三季报点评：现金流大幅提升，国际绿色矿山订单彰显竞争力",
      "研究机构": "财信证券"
    },
    {
      "序号": 181,
      "报告日期": "2025-11-01",
      "证券代码": "603583",
      "证券简称": "捷昌驱动",
      "评级": "增持",
      "评级变化": "维持",
      "目标价": "45.00",
      "EPS实际值(元)": "0.74(2024)",
      "T年度": "2025",
      "EPS预测": {
        "T年": "--",
        "T+1年": "--",
        "T+2年": "--"
      },
      "标题": "捷昌驱动(603583)全球化深入布局，智能化持续突破",
      "研究机构": "中金公司"
    },
    {
      "序号": 182,
      "报告日期": "2025-11-01",
      "证券代码": "603697",
      "证券简称": "有友食品",
      "评级": "增持",
      "评级变化": "维持",
      "目标价": "16.50",
      "EPS实际值(元)": "0.37(2024)",
      "T年度": "2025",
      "EPS预测": {
        "T年": "--",
        "T+1年": "--",
        "T+2年": "--"
      },
      "标题": "有友食品(603697)3Q25新渠道放量持续，业绩超市场预期",
      "研究机构": "中金公司"
    },
    {
      "序号": 183,
      "报告日期": "2025-11-01",
      "证券代码": "603885",
      "证券简称": "吉祥航空",
      "评级": "增持",
      "评级变化": "维持",
      "目标价": "--",
      "EPS实际值(元)": "0.42(2024)",
      "T年度": "2025",
      "EPS预测": {
        "T年": "--",
        "T+1年": "--",
        "T+2年": "--"
      },
      "标题": "吉祥航空(603885)3季度业绩不及预期，重拾增长可期",
      "研究机构": "中金公司"
    },
    {
      "序号": 184,
      "报告日期": "2025-11-01",
      "证券代码": "688507",
      "证券简称": "索辰科技",
      "评级": "买入",
      "评级变化": "维持",
      "目标价": "--",
      "EPS实际值(元)": "0.47(2024)",
      "T年度": "2025",
      "EPS预测": {
        "T年": "0.84",
        "T+1年": "1.41",
        "T+2年": "1.74"
      },
      "标题": "索辰科技(688507)Q3营收快速增长，物理AI商业化与收并购并行推进",
      "研究机构": "中泰证券"
    },
    {
      "序号": 185,
      "报告日期": "2025-11-01",
      "证券代码": "688059",
      "证券简称": "华锐精密",
      "评级": "增持",
      "评级变化": "维持",
      "目标价": "100.00",
      "EPS实际值(元)": "1.73(2024)",
      "T年度": "2025",
      "EPS预测": {
        "T年": "--",
        "T+1年": "--",
        "T+2年": "--"
      },
      "标题": "华锐精密(688059)Q3业绩同比高增，新兴行业解决方案加速成长",
      "研究机构": "中金公司"
    },
    {
      "序号": 186,
      "报告日期": "2025-11-01",
      "证券代码": "688239",
      "证券简称": "航宇科技",
      "评级": "增持",
      "评级变化": "维持",
      "目标价": "55.31",
      "EPS实际值(元)": "1.3(2024)",
      "T年度": "2025",
      "EPS预测": {
        "T年": "--",
        "T+1年": "--",
        "T+2年": "--"
      },
      "标题": "航宇科技(688239)3Q25业绩符合预期，一体化交付战略加速落地",
      "研究机构": "中金公司"
    },
    {
      "序号": 187,
      "报告日期": "2025-11-01",
      "证券代码": "688385",
      "证券简称": "复旦微电",
      "评级": "增持",
      "评级变化": "维持",
      "目标价": "67.42",
      "EPS实际值(元)": "0.7(2024)",
      "T年度": "2025",
      "EPS预测": {
        "T年": "--",
        "T+1年": "--",
        "T+2年": "--"
      },
      "标题": "复旦微电(688385)FPGA龙头地位稳固，AI与卫星打开长期空间",
      "研究机构": "中金公司"
    },
    {
      "序号": 188,
      "报告日期": "2025-11-01",
      "证券代码": "688396",
      "证券简称": "华润微",
      "评级": "增持",
      "评级变化": "维持",
      "目标价": "53.11",
      "EPS实际值(元)": "0.5765(2024)",
      "T年度": "2025",
      "EPS预测": {
        "T年": "--",
        "T+1年": "--",
        "T+2年": "--"
      },
      "标题": "华润微(688396)3Q25收入利润同比稳定增长",
      "研究机构": "中金公司"
    },
    {
      "序号": 189,
      "报告日期": "2025-11-01",
      "证券代码": "688498",
      "证券简称": "源杰科技",
      "评级": "增持",
      "评级变化": "维持",
      "目标价": "560.00",
      "EPS实际值(元)": "-0.07(2024)",
      "T年度": "2025",
      "EPS预测": {
        "T年": "--",
        "T+1年": "--",
        "T+2年": "--"
      },
      "标题": "源杰科技(688498)CW放量提振盈利水平，积极扩产应对强劲需求",
      "研究机构": "中金公司"
    },
    {
      "序号": 190,
      "报告日期": "2025-11-01",
      "证券代码": "688680",
      "证券简称": "海优新材",
      "评级": "增持",
      "评级变化": "维持",
      "目标价": "52.31",
      "EPS实际值(元)": "-6.73(2024)",
      "T年度": "2025",
      "EPS预测": {
        "T年": "--",
        "T+1年": "--",
        "T+2年": "--"
      },
      "标题": "海优新材(688680)3Q25业绩符合预期，调光膜材料快速突破",
      "研究机构": "中金公司"
    },
    {
      "序号": 191,
      "报告日期": "2025-11-01",
      "证券代码": "688772",
      "证券简称": "珠海冠宇",
      "评级": "增持",
      "评级变化": "维持",
      "目标价": "31.00",
      "EPS实际值(元)": "0.38(2024)",
      "T年度": "2025",
      "EPS预测": {
        "T年": "--",
        "T+1年": "--",
        "T+2年": "--"
      },
      "标题": "珠海冠宇(688772)3Q25业绩符合预告，北美客户放量伴新品导入",
      "研究机构": "中金公司"
    },
    {
      "序号": 192,
      "报告日期": "2025-11-01",
      "证券代码": "002352",
      "证券简称": "顺丰控股",
      "评级": "买入",
      "评级变化": "维持",
      "目标价": "--",
      "EPS实际值(元)": "2.11(2024)",
      "T年度": "2025",
      "EPS预测": {
        "T年": "2.22",
        "T+1年": "2.59",
        "T+2年": "3.01"
      },
      "标题": "顺丰控股(002352)2025年三季报点评：“先有后优”从规模驱动到价值驱动，Q4经营状况有望改善",
      "研究机构": "国联民生"
    },
    {
      "序号": 193,
      "报告日期": "2025-11-01",
      "证券代码": "688799",
      "证券简称": "华纳药厂",
      "评级": "买入",
      "评级变化": "维持",
      "目标价": "--",
      "EPS实际值(元)": "1.75(2024)",
      "T年度": "2025",
      "EPS预测": {
        "T年": "1.73",
        "T+1年": "1.80",
        "T+2年": "2.00"
      },
      "标题": "华纳药厂(688799)公司点评报告：三季度经营改善明显，创新药稳步推进",
      "研究机构": "方正证券"
    },
    {
      "序号": 194,
      "报告日期": "2025-11-01",
      "证券代码": "000498",
      "证券简称": "山东路桥",
      "评级": "买入",
      "评级变化": "维持",
      "目标价": "9.26",
      "EPS实际值(元)": "1.2281(2024)",
      "T年度": "2025",
      "EPS预测": {
        "T年": "1.52",
        "T+1年": "1.54",
        "T+2年": "1.58"
      },
      "标题": "山东路桥(000498)前三季度新签订单快速增长",
      "研究机构": "华泰证券"
    },
    {
      "序号": 195,
      "报告日期": "2025-11-01",
      "证券代码": "000800",
      "证券简称": "一汽解放",
      "评级": "买入",
      "评级变化": "维持",
      "目标价": "--",
      "EPS实际值(元)": "0.1266(2024)",
      "T年度": "2025",
      "EPS预测": {
        "T年": "0.15",
        "T+1年": "0.21",
        "T+2年": "0.27"
      },
      "标题": "一汽解放(000800)2025年三季报点评：Q3归母净利润转正，盈利改善持续性可期",
      "研究机构": "东吴证券"
    },
    {
      "序号": 196,
      "报告日期": "2025-11-01",
      "证券代码": "301061",
      "证券简称": "匠心家居",
      "评级": "未知",
      "评级变化": "未知",
      "目标价": "--",
      "EPS实际值(元)": "4.1(2024)",
      "T年度": "2025",
      "EPS预测": {
        "T年": "4.30",
        "T+1年": "5.31",
        "T+2年": "6.39"
      },
      "标题": "匠心家居(301061)客户拓展、产品改善，持续高速成长",
      "研究机构": "信达证券"
    },
    {
      "序号": 197,
      "报告日期": "2025-11-01",
      "证券代码": "000811",
      "证券简称": "冰轮环境",
      "评级": "未知",
      "评级变化": "未知",
      "目标价": "--",
      "EPS实际值(元)": "0.82(2024)",
      "T年度": "2025",
      "EPS预测": {
        "T年": "0.67",
        "T+1年": "0.77",
        "T+2年": "0.93"
      },
      "标题": "冰轮环境(000811)单三季度业绩稳步增长，看好公司数据中心及液冷系统出海",
      "研究机构": "信达证券"
    },
    {
      "序号": 198,
      "报告日期": "2025-11-01",
      "证券代码": "000938",
      "证券简称": "紫光股份",
      "评级": "买入",
      "评级变化": "维持",
      "目标价": "--",
      "EPS实际值(元)": "0.5498(2024)",
      "T年度": "2025",
      "EPS预测": {
        "T年": "0.62",
        "T+1年": "0.90",
        "T+2年": "1.11"
      },
      "标题": "紫光股份(000938)公司信息更新报告：业绩短期承压，超节点产品规模部署",
      "研究机构": "开源证券"
    },
    {
      "序号": 199,
      "报告日期": "2025-11-01",
      "证券代码": "000977",
      "证券简称": "浪潮信息",
      "评级": "买入",
      "评级变化": "维持",
      "目标价": "83.20",
      "EPS实际值(元)": "1.5568(2024)",
      "T年度": "2025",
      "EPS预测": {
        "T年": "1.91",
        "T+1年": "2.56",
        "T+2年": "3.29"
      },
      "标题": "浪潮信息(000977)合同负债高增，把握AI机遇",
      "研究机构": "华泰证券"
    },
    {
      "序号": 200,
      "报告日期": "2025-11-01",
      "证券代码": "600138",
      "证券简称": "中青旅",
      "评级": "增持",
      "评级变化": "维持",
      "目标价": "10.56",
      "EPS实际值(元)": "0.22(2024)",
      "T年度": "2025",
      "EPS预测": {
        "T年": "0.19",
        "T+1年": "0.23",
        "T+2年": "0.32"
      },
      "标题": "中青旅(600138)业务结构调整影响利润表现",
      "研究机构": "华泰证券"
    },
    {
      "序号": 201,
      "报告日期": "2025-11-01",
      "证券代码": "600612",
      "证券简称": "老凤祥",
      "评级": "买入",
      "评级变化": "维持",
      "目标价": "--",
      "EPS实际值(元)": "3.7273(2024)",
      "T年度": "2025",
      "EPS预测": {
        "T年": "3.17",
        "T+1年": "3.52",
        "T+2年": "3.78"
      },
      "标题": "老凤祥(600612)25Q3：Q3收入增长稳健，利润端短期承压",
      "研究机构": "信达证券"
    },
    {
      "序号": 202,
      "报告日期": "2025-11-01",
      "证券代码": "002179",
      "证券简称": "中航光电",
      "评级": "买入",
      "评级变化": "维持",
      "目标价": "40.50",
      "EPS实际值(元)": "1.6091(2024)",
      "T年度": "2025",
      "EPS预测": {
        "T年": "1.12",
        "T+1年": "1.35",
        "T+2年": "1.62"
      },
      "标题": "中航光电(002179)防务确收等多因素导致Q3业绩承压，看好公司军民协同中长期发展",
      "研究机构": "东方证券"
    },
    {
      "序号": 203,
      "报告日期": "2025-11-01",
      "证券代码": "601618",
      "证券简称": "中国中冶",
      "评级": "增持",
      "评级变化": "维持",
      "目标价": "4.08",
      "EPS实际值(元)": "0.24(2024)",
      "T年度": "2025",
      "EPS预测": {
        "T年": "0.30",
        "T+1年": "0.31",
        "T+2年": "0.33"
      },
      "标题": "中国中冶(601618)减值和应收短期继续扰动Q3业绩",
      "研究机构": "华泰证券"
    },
    {
      "序号": 204,
      "报告日期": "2025-11-01",
      "证券代码": "601689",
      "证券简称": "拓普集团",
      "评级": "买入",
      "评级变化": "维持",
      "目标价": "90.29",
      "EPS实际值(元)": "1.79(2024)",
      "T年度": "2025",
      "EPS预测": {
        "T年": "1.64",
        "T+1年": "2.02",
        "T+2年": "2.55"
      },
      "标题": "拓普集团(601689)液冷、机器人、车端业务协同并进",
      "研究机构": "华泰证券"
    },
    {
      "序号": 205,
      "报告日期": "2025-11-01",
      "证券代码": "002444",
      "证券简称": "巨星科技",
      "评级": "买入",
      "评级变化": "维持",
      "目标价": "38.36",
      "EPS实际值(元)": "1.9286(2024)",
      "T年度": "2025",
      "EPS预测": {
        "T年": "2.21",
        "T+1年": "2.74",
        "T+2年": "3.32"
      },
      "标题": "巨星科技(002444)短期海外需求波动，期待终端回暖",
      "研究机构": "华泰证券"
    },
    {
      "序号": 206,
      "报告日期": "2025-11-01",
      "证券代码": "601800",
      "证券简称": "中国交建",
      "评级": "买入",
      "评级变化": "首次",
      "目标价": "10.71",
      "EPS实际值(元)": "1.37(2024)",
      "T年度": "2025",
      "EPS预测": {
        "T年": "1.50",
        "T+1年": "1.53",
        "T+2年": "1.54"
      },
      "标题": "中国交建(601800)2025年三季报点评：新兴业务表现亮眼，经营性现金流同比改善",
      "研究机构": "西南证券"
    },
    {
      "序号": 207,
      "报告日期": "2025-11-01",
      "证券代码": "603225",
      "证券简称": "新凤鸣",
      "评级": "买入",
      "评级变化": "维持",
      "目标价": "--",
      "EPS实际值(元)": "0.73(2024)",
      "T年度": "2025",
      "EPS预测": {
        "T年": "0.73",
        "T+1年": "1.34",
        "T+2年": "1.67"
      },
      "标题": "新凤鸣(603225)公司信息更新报告：长丝供需格局向好，PTA或将否极泰来",
      "研究机构": "开源证券"
    },
    {
      "序号": 208,
      "报告日期": "2025-11-01",
      "证券代码": "002812",
      "证券简称": "恩捷股份",
      "评级": "买入",
      "评级变化": "维持",
      "目标价": "--",
      "EPS实际值(元)": "-0.57(2024)",
      "T年度": "2025",
      "EPS预测": {
        "T年": "0.01",
        "T+1年": "1.25",
        "T+2年": "2.07"
      },
      "标题": "恩捷股份(002812)2025年三季报点评：盈利底部有望迎来价格拐点，布局硫化锂打造第二增长曲线",
      "研究机构": "东吴证券"
    }
  ]
}