{
  "获取时间": "2026-02-18 18:42:10",
  "数据日期": "2026-01-25",
  "数据条数": 36,
  "研报数据": [
    {
      "序号": 1,
      "报告日期": "2026-01-25",
      "证券代码": "000524",
      "证券简称": "岭南控股",
      "评级": "增持",
      "评级变化": "首次",
      "目标价": "--",
      "EPS实际值(元)": "0.22(2024)",
      "T年度": "2025",
      "EPS预测": {
        "T年": "0.20",
        "T+1年": "0.27",
        "T+2年": "0.35"
      },
      "标题": "岭南控股(000524)广州市属文旅企业，业务全国化及多元化发展并行",
      "研究机构": "华源证券"
    },
    {
      "序号": 2,
      "报告日期": "2026-01-25",
      "证券代码": "000543",
      "证券简称": "皖能电力",
      "评级": "买入",
      "评级变化": "维持",
      "目标价": "--",
      "EPS实际值(元)": "0.91(2024)",
      "T年度": "2025",
      "EPS预测": {
        "T年": "1.03",
        "T+1年": "1.05",
        "T+2年": "1.06"
      },
      "标题": "皖能电力(000543)拟增资控股新能公司，优化公司主营业务布局",
      "研究机构": "天风证券"
    },
    {
      "序号": 3,
      "报告日期": "2026-01-25",
      "证券代码": "001221",
      "证券简称": "悍高集团",
      "评级": "买入",
      "评级变化": "首次",
      "目标价": "74.76",
      "EPS实际值(元)": "1.48(2024)",
      "T年度": "2025",
      "EPS预测": {
        "T年": "1.88",
        "T+1年": "2.49",
        "T+2年": "3.27"
      },
      "标题": "悍高集团(001221)五金龙头，高速进击",
      "研究机构": "国金证券"
    },
    {
      "序号": 4,
      "报告日期": "2026-01-25",
      "证券代码": "002027",
      "证券简称": "分众传媒",
      "评级": "买入",
      "评级变化": "维持",
      "目标价": "--",
      "EPS实际值(元)": "0.357(2024)",
      "T年度": "2025",
      "EPS预测": {
        "T年": "0.24",
        "T+1年": "0.42",
        "T+2年": "0.43"
      },
      "标题": "分众传媒(002027)数禾减值系一次性非经常影响，不影响公司分红能力",
      "研究机构": "招商证券"
    },
    {
      "序号": 5,
      "报告日期": "2026-01-25",
      "证券代码": "002027",
      "证券简称": "分众传媒",
      "评级": "买入",
      "评级变化": "维持",
      "目标价": "--",
      "EPS实际值(元)": "0.357(2024)",
      "T年度": "2025",
      "EPS预测": {
        "T年": "0.20",
        "T+1年": "0.42",
        "T+2年": "0.43"
      },
      "标题": "分众传媒(002027)计提数禾资产减值，分红金额及梯媒主业不受影响",
      "研究机构": "申万宏源"
    },
    {
      "序号": 6,
      "报告日期": "2026-01-25",
      "证券代码": "002340",
      "证券简称": "格林美",
      "评级": "买入",
      "评级变化": "首次",
      "目标价": "--",
      "EPS实际值(元)": "0.2(2024)",
      "T年度": "2025",
      "EPS预测": {
        "T年": "0.32",
        "T+1年": "0.45",
        "T+2年": "0.69"
      },
      "标题": "格林美(002340)公司动态研究报告：正极材料不断突破，镍钴自供能力强化",
      "研究机构": "华鑫证券"
    },
    {
      "序号": 7,
      "报告日期": "2026-01-25",
      "证券代码": "002558",
      "证券简称": "巨人网络",
      "评级": "增持",
      "评级变化": "首次",
      "目标价": "--",
      "EPS实际值(元)": "0.78(2024)",
      "T年度": "2025",
      "EPS预测": {
        "T年": "1.62",
        "T+1年": "3.05",
        "T+2年": "3.43"
      },
      "标题": "巨人网络(002558)长青IP铸就基本盘，休闲赛道打开向上空间",
      "研究机构": "国信证券"
    },
    {
      "序号": 8,
      "报告日期": "2026-01-25",
      "证券代码": "002615",
      "证券简称": "哈尔斯",
      "评级": "买入",
      "评级变化": "维持",
      "目标价": "--",
      "EPS实际值(元)": "0.63(2024)",
      "T年度": "2025",
      "EPS预测": {
        "T年": "0.24",
        "T+1年": "0.56",
        "T+2年": "0.83"
      },
      "标题": "哈尔斯(002615)行业出口维持高增，制造&品牌共驱成长",
      "研究机构": "信达证券"
    },
    {
      "序号": 9,
      "报告日期": "2026-01-25",
      "证券代码": "002891",
      "证券简称": "中宠股份",
      "评级": "未知",
      "评级变化": "未知",
      "目标价": "--",
      "EPS实际值(元)": "1.3399(2024)",
      "T年度": "2025",
      "EPS预测": {
        "T年": "1.51",
        "T+1年": "1.89",
        "T+2年": "2.27"
      },
      "标题": "中宠股份(002891)回购股份彰显信心，经营态势良好",
      "研究机构": "信达证券"
    },
    {
      "序号": 10,
      "报告日期": "2026-01-25",
      "证券代码": "002895",
      "证券简称": "川恒股份",
      "评级": "买入",
      "评级变化": "首次",
      "目标价": "50.73",
      "EPS实际值(元)": "1.7647(2024)",
      "T年度": "2025",
      "EPS预测": {
        "T年": "2.16",
        "T+1年": "2.67",
        "T+2年": "2.96"
      },
      "标题": "川恒股份(002895)受益于行业高景气的磷化工一体化企业",
      "研究机构": "华泰证券"
    },
    {
      "序号": 11,
      "报告日期": "2026-01-25",
      "证券代码": "600036",
      "证券简称": "招商银行",
      "评级": "买入",
      "评级变化": "维持",
      "目标价": "--",
      "EPS实际值(元)": "5.66(2024)",
      "T年度": "2025",
      "EPS预测": {
        "T年": "6.05",
        "T+1年": "6.33",
        "T+2年": "6.64"
      },
      "标题": "招商银行(600036)2025年业绩快报点评：营收盈利增速双升，不良贷款率维持低位",
      "研究机构": "光大证券"
    },
    {
      "序号": 12,
      "报告日期": "2026-01-25",
      "证券代码": "600036",
      "证券简称": "招商银行",
      "评级": "买入",
      "评级变化": "维持",
      "目标价": "--",
      "EPS实际值(元)": "5.66(2024)",
      "T年度": "2025",
      "EPS预测": {
        "T年": "5.70",
        "T+1年": "5.85",
        "T+2年": "6.07"
      },
      "标题": "招商银行(600036)稳健高股息优势突出，聚焦红利逻辑下估值修复弹性",
      "研究机构": "申万宏源"
    },
    {
      "序号": 13,
      "报告日期": "2026-01-25",
      "证券代码": "600160",
      "证券简称": "巨化股份",
      "评级": "买入",
      "评级变化": "维持",
      "目标价": "--",
      "EPS实际值(元)": "0.73(2024)",
      "T年度": "2025",
      "EPS预测": {
        "T年": "1.41",
        "T+1年": "2.17",
        "T+2年": "2.70"
      },
      "标题": "巨化股份(600160)2025年业绩预增点评：2025年公司归母净利润同比大幅提升，看好制冷剂景气持续",
      "研究机构": "国海证券"
    },
    {
      "序号": 14,
      "报告日期": "2026-01-25",
      "证券代码": "600189",
      "证券简称": "泉阳泉",
      "评级": "买入",
      "评级变化": "调高",
      "目标价": "--",
      "EPS实际值(元)": "0.01(2024)",
      "T年度": "2025",
      "EPS预测": {
        "T年": "0.02",
        "T+1年": "0.03",
        "T+2年": "0.04"
      },
      "标题": "泉阳泉(600189)剥离非主业轻装上阵，聚焦矿泉水主业提质增效",
      "研究机构": "中泰证券"
    },
    {
      "序号": 15,
      "报告日期": "2026-01-25",
      "证券代码": "600926",
      "证券简称": "杭州银行",
      "评级": "买入",
      "评级变化": "维持",
      "目标价": "--",
      "EPS实际值(元)": "2.74(2024)",
      "T年度": "2025",
      "EPS预测": {
        "T年": "2.72",
        "T+1年": "3.18",
        "T+2年": "3.71"
      },
      "标题": "杭州银行(600926)2025年业绩快报点评：贷款增速稳中有进，五年规划圆满收官",
      "研究机构": "光大证券"
    },
    {
      "序号": 16,
      "报告日期": "2026-01-25",
      "证券代码": "600926",
      "证券简称": "杭州银行",
      "评级": "买入",
      "评级变化": "维持",
      "目标价": "17.90",
      "EPS实际值(元)": "2.74(2024)",
      "T年度": "2025",
      "EPS预测": {
        "T年": "2.54",
        "T+1年": "2.83",
        "T+2年": "3.14"
      },
      "标题": "杭州银行(600926)2025年业绩快报点评：理财规模同比增39以上",
      "研究机构": "国泰海通"
    },
    {
      "序号": 17,
      "报告日期": "2026-01-25",
      "证券代码": "601615",
      "证券简称": "明阳智能",
      "评级": "买入",
      "评级变化": "维持",
      "目标价": "--",
      "EPS实际值(元)": "0.15(2024)",
      "T年度": "2025",
      "EPS预测": {
        "T年": "0.34",
        "T+1年": "0.93",
        "T+2年": "1.40"
      },
      "标题": "明阳智能(601615)拟发行股份及现金支付收购德华芯片100%股权，太空光伏砷化镓／钙钛矿／HJT三大技术并驾齐驱",
      "研究机构": "东吴证券"
    },
    {
      "序号": 18,
      "报告日期": "2026-01-25",
      "证券代码": "601689",
      "证券简称": "拓普集团",
      "评级": "买入",
      "评级变化": "维持",
      "目标价": "--",
      "EPS实际值(元)": "1.79(2024)",
      "T年度": "2025",
      "EPS预测": {
        "T年": "1.63",
        "T+1年": "2.08",
        "T+2年": "2.79"
      },
      "标题": "拓普集团(601689)公司深度报告：从车到人形机器人，大象轻盈起舞",
      "研究机构": "开源证券"
    },
    {
      "序号": 19,
      "报告日期": "2026-01-25",
      "证券代码": "603135",
      "证券简称": "中重科技",
      "评级": "买入",
      "评级变化": "首次",
      "目标价": "--",
      "EPS实际值(元)": "0.09(2024)",
      "T年度": "2025",
      "EPS预测": {
        "T年": "-0.03",
        "T+1年": "0.31",
        "T+2年": "0.64"
      },
      "标题": "中重科技(603135)海外爆发、国内修复，今年有望迎来业绩拐点",
      "研究机构": "中信建投"
    },
    {
      "序号": 20,
      "报告日期": "2026-01-25",
      "证券代码": "605016",
      "证券简称": "百龙创园",
      "评级": "买入",
      "评级变化": "维持",
      "目标价": "--",
      "EPS实际值(元)": "0.76(2024)",
      "T年度": "2025",
      "EPS预测": {
        "T年": "0.87",
        "T+1年": "1.11",
        "T+2年": "1.45"
      },
      "标题": "百龙创园(605016)业绩再创新高，增长动能持续夯实",
      "研究机构": "信达证券"
    },
    {
      "序号": 21,
      "报告日期": "2026-01-25",
      "证券代码": "688059",
      "证券简称": "华锐精密",
      "评级": "买入",
      "评级变化": "维持",
      "目标价": "--",
      "EPS实际值(元)": "1.73(2024)",
      "T年度": "2025",
      "EPS预测": {
        "T年": "1.93",
        "T+1年": "2.50",
        "T+2年": "3.35"
      },
      "标题": "华锐精密(688059)点评报告：年报预告符合预期，人形机器人、AI软件驱动公司二次腾飞",
      "研究机构": "浙商证券"
    },
    {
      "序号": 22,
      "报告日期": "2026-01-25",
      "证券代码": "688233",
      "证券简称": "神工股份",
      "评级": "买入",
      "评级变化": "维持",
      "目标价": "--",
      "EPS实际值(元)": "0.24(2024)",
      "T年度": "2025",
      "EPS预测": {
        "T年": "0.62",
        "T+1年": "1.30",
        "T+2年": "1.87"
      },
      "标题": "神工股份(688233)硅零部件连续3年高增，刻蚀硅材料景气回归",
      "研究机构": "申万宏源"
    },
    {
      "序号": 23,
      "报告日期": "2026-01-25",
      "证券代码": "688521",
      "证券简称": "芯原股份",
      "评级": "买入",
      "评级变化": "维持",
      "目标价": "--",
      "EPS实际值(元)": "-1.2(2024)",
      "T年度": "2025",
      "EPS预测": {
        "T年": "-0.85",
        "T+1年": "-0.33",
        "T+2年": "0.64"
      },
      "标题": "芯原股份(688521)AI与数据处理芯片需求引领，在手订单逾50亿",
      "研究机构": "申万宏源"
    },
    {
      "序号": 24,
      "报告日期": "2026-01-25",
      "证券代码": "688717",
      "证券简称": "艾罗能源",
      "评级": "买入",
      "评级变化": "维持",
      "目标价": "--",
      "EPS实际值(元)": "1.27(2024)",
      "T年度": "2025",
      "EPS预测": {
        "T年": "0.65",
        "T+1年": "4.34",
        "T+2年": "8.70"
      },
      "标题": "艾罗能源(688717)持续的前瞻投入，有望迎来收获",
      "研究机构": "招商证券"
    },
    {
      "序号": 25,
      "报告日期": "2026-01-25",
      "证券代码": "920208",
      "证券简称": "青矩技术",
      "评级": "增持",
      "评级变化": "首次",
      "目标价": "--",
      "EPS实际值(元)": "1.94(2024)",
      "T年度": "2025",
      "EPS预测": {
        "T年": "1.43",
        "T+1年": "1.61",
        "T+2年": "1.79"
      },
      "标题": "青矩技术(920208)全过程工程咨询服务领军者，积极布局AI推行数智化咨询新模式",
      "研究机构": "华源证券"
    },
    {
      "序号": 26,
      "报告日期": "2026-01-25",
      "证券代码": "002851",
      "证券简称": "麦格米特",
      "评级": "增持",
      "评级变化": "维持",
      "目标价": "--",
      "EPS实际值(元)": "0.8651(2024)",
      "T年度": "2025",
      "EPS预测": {
        "T年": "0.63",
        "T+1年": "2.73",
        "T+2年": "4.55"
      },
      "标题": "麦格米特(002851)主业有望企稳，AI电源业务进展顺利",
      "研究机构": "招商证券"
    },
    {
      "序号": 27,
      "报告日期": "2026-01-25",
      "证券代码": "603986",
      "证券简称": "兆易创新",
      "评级": "买入",
      "评级变化": "维持",
      "目标价": "--",
      "EPS实际值(元)": "1.66(2024)",
      "T年度": "2025",
      "EPS预测": {
        "T年": "2.31",
        "T+1年": "3.26",
        "T+2年": "4.04"
      },
      "标题": "兆易创新(603986)AI基建叠加存储周期上行，带动公司业绩增长",
      "研究机构": "华金证券"
    },
    {
      "序号": 28,
      "报告日期": "2026-01-25",
      "证券代码": "300483",
      "证券简称": "首华燃气",
      "评级": "买入",
      "评级变化": "维持",
      "目标价": "--",
      "EPS实际值(元)": "-2.687(2024)",
      "T年度": "2025",
      "EPS预测": {
        "T年": "0.54",
        "T+1年": "1.09",
        "T+2年": "1.88"
      },
      "标题": "首华燃气(300483)2025年度业绩预告点评：深层煤层气先行者扭亏为盈",
      "研究机构": "东吴证券"
    },
    {
      "序号": 29,
      "报告日期": "2026-01-25",
      "证券代码": "601330",
      "证券简称": "绿色动力",
      "评级": "买入",
      "评级变化": "维持",
      "目标价": "--",
      "EPS实际值(元)": "0.42(2024)",
      "T年度": "2025",
      "EPS预测": {
        "T年": "0.47",
        "T+1年": "0.51",
        "T+2年": "0.55"
      },
      "标题": "绿色动力(601330)审议通过新密项目收购，强化区位协同，提分红+提ROE逻辑不改",
      "研究机构": "东吴证券"
    },
    {
      "序号": 30,
      "报告日期": "2026-01-25",
      "证券代码": "603011",
      "证券简称": "合锻智能",
      "评级": "买入",
      "评级变化": "维持",
      "目标价": "--",
      "EPS实际值(元)": "-0.18(2024)",
      "T年度": "2025",
      "EPS预测": {
        "T年": "-0.39",
        "T+1年": "0.19",
        "T+2年": "0.41"
      },
      "标题": "合锻智能(603011)2025年业绩预告点评：主业短期承压致25年亏损，新中标BEST包层系统屏蔽块项目，进一步拓展核聚变领域",
      "研究机构": "华创证券"
    },
    {
      "序号": 31,
      "报告日期": "2026-01-25",
      "证券代码": "688008",
      "证券简称": "澜起科技",
      "评级": "买入",
      "评级变化": "维持",
      "目标价": "--",
      "EPS实际值(元)": "1.25(2024)",
      "T年度": "2025",
      "EPS预测": {
        "T年": "1.99",
        "T+1年": "2.81",
        "T+2年": "3.88"
      },
      "标题": "澜起科技(688008)科创板公司动态研究：2025年业绩预增50%++AI推理或拉动互连芯片需求",
      "研究机构": "国海证券"
    },
    {
      "序号": 32,
      "报告日期": "2026-01-25",
      "证券代码": "002891",
      "证券简称": "中宠股份",
      "评级": "买入",
      "评级变化": "维持",
      "目标价": "79.64",
      "EPS实际值(元)": "1.3399(2024)",
      "T年度": "2025",
      "EPS预测": {
        "T年": "1.42",
        "T+1年": "1.81",
        "T+2年": "2.38"
      },
      "标题": "中宠股份(002891)回购股票彰显长期增长信心",
      "研究机构": "华泰证券"
    },
    {
      "序号": 33,
      "报告日期": "2026-01-25",
      "证券代码": "300115",
      "证券简称": "长盈精密",
      "评级": "增持",
      "评级变化": "维持",
      "目标价": "--",
      "EPS实际值(元)": "0.6(2024)",
      "T年度": "2025",
      "EPS预测": {
        "T年": "0.44",
        "T+1年": "0.75",
        "T+2年": "1.00"
      },
      "标题": "长盈精密(300115)股权激励授予落地，继续看好公司在机器人赛道的卡位优势",
      "研究机构": "招商证券"
    },
    {
      "序号": 34,
      "报告日期": "2026-01-25",
      "证券代码": "300602",
      "证券简称": "飞荣达",
      "评级": "买入",
      "评级变化": "维持",
      "目标价": "--",
      "EPS实际值(元)": "0.33(2024)",
      "T年度": "2025",
      "EPS预测": {
        "T年": "0.71",
        "T+1年": "1.49",
        "T+2年": "2.04"
      },
      "标题": "飞荣达(300602)2025年度业绩预告点评：预计2025年营收同比增长约25%，盈利能力稳步上升",
      "研究机构": "国海证券"
    },
    {
      "序号": 35,
      "报告日期": "2026-01-25",
      "证券代码": "601009",
      "证券简称": "南京银行",
      "评级": "买入",
      "评级变化": "维持",
      "目标价": "--",
      "EPS实际值(元)": "1.83(2024)",
      "T年度": "2025",
      "EPS预测": {
        "T年": "1.73",
        "T+1年": "1.94",
        "T+2年": "2.17"
      },
      "标题": "南京银行(601009)2025年业绩快报点评：2025Q4单季度营收增速达到16%，灵活调整金融资产结构",
      "研究机构": "国海证券"
    },
    {
      "序号": 36,
      "报告日期": "2026-01-25",
      "证券代码": "601799",
      "证券简称": "星宇股份",
      "评级": "增持",
      "评级变化": "维持",
      "目标价": "--",
      "EPS实际值(元)": "4.9628(2024)",
      "T年度": "2025",
      "EPS预测": {
        "T年": "5.91",
        "T+1年": "7.38",
        "T+2年": "9.24"
      },
      "标题": "星宇股份(601799)携手产业链推进Micro-LED国产化，车灯业务量价双升",
      "研究机构": "国信证券"
    }
  ]
}